ParkingSystem/Location.v
// The module returns the first 0 it founds in input.
// if there is any park it returns index. 0 to 3

// And if there isn't any park spot, full state, it returns 5. 101

module Location (
    input  wire [3:0] in,
    output wire [2:0] encoded
);

  wire not_in3, not_in2, not_in1, not_in0;
  wire and0, and1, and2;


  not U0 (not_in3, in[3]);
  not U1 (not_in2, in[2]);
  not U2 (not_in1, in[1]);
  not U3 (not_in0, in[0]);

  and U4 (and0, not_in1, in[0]);
  and U5 (and1, not_in2, in[1], in[0]);
  and U6 (and2, not_in3, in[2], in[1], in[0]);

  and U7 (encoded[2], in[3], in[2], in[1], in[0]);


  or U8 (encoded[1], and2, and1);
  or U9 (encoded[0], encoded[2], and2, and0);


endmodule

ParkingSystem/Location_tb.v
`timescale 1 ns / 1 ps

module Location_tb;

  reg  [3:0] in;
  wire [2:0] encoded;

  Location UUT (
      .in (in),
      .encoded(encoded)
  );

  initial begin
    $dumpfile("Location_tb.vcd");
    $dumpvars(0, Location_tb);

  end

  initial begin
    in = 4'b0001;
    #100;

    in = 4'b0000;
    #100;

    in = 4'b0100;
    #100;

    in = 4'b1010;
    #100;

    in = 4'b1111;
    #100;

    in = 4'b1110;
    #100;

    in = 4'b0111;
    #100;

  end

endmodule

ParkingSystem/FSM.v
module FSM (
    input  wire       clk,             // Clock signal
    input  wire [3:0] in,              // 4-bit input: {EnterSensor, ExitSensor, ExitPlace[1:0]}
    output reg  [3:0] state,           // 4-bit state representing the parking spots
    output reg        door_open_pulse  // Pulse for door open LED
);

  // Initialization
  initial begin
    state           = 4'b0000;  // Initial state: all parking spots empty
    door_open_pulse = 1'b0;     // Door open LED initially off
  end

reg [3:0] next_state; // Internal signal to store the next state

  always @(posedge clk) begin
    next_state = state;   // Default next state is the current state

    case (in[3:2])  // Check the input format
      2'b10: begin  // Enter sensor triggered, Exit sensor not triggered
        if (state != 4'b1111) begin  // Parking not full
          // Find the first empty parking spot (rightmost 0 becomes 1)
          case (state)
            4'b0000: next_state = 4'b0001;
            4'b0001: next_state = 4'b0011;
            4'b0010: next_state = 4'b0011;
            4'b0011: next_state = 4'b0111;
            4'b0100: next_state = 4'b0101;
            4'b0101: next_state = 4'b0111;
            4'b0110: next_state = 4'b0111;
            4'b0111: next_state = 4'b1111;
            4'b1000: next_state = 4'b1001;
            4'b1001: next_state = 4'b1011;
            4'b1010: next_state = 4'b1011;
            4'b1011: next_state = 4'b1111;
            4'b1100: next_state = 4'b1101;
            4'b1101: next_state = 4'b1111;
            4'b1110: next_state = 4'b1111;
            default: next_state = state; // Default to current state
          endcase
        end
      end

      2'b01: begin  // Exit sensor triggered, Enter sensor not triggered
        // Check the exit place validity and remove the car
        case (in[1:0])  // ExitPlace
          2'b00: if (state[0]) next_state = state & 4'b1110;  // Exit from spot 0
          2'b01: if (state[1]) next_state = state & 4'b1101;  // Exit from spot 1
          2'b10: if (state[2]) next_state = state & 4'b1011;  // Exit from spot 2
          2'b11: if (state[3]) next_state = state & 4'b0111;  // Exit from spot 3
          default: next_state = state; // Invalid exit place, keep current state
        endcase
      end

      default: next_state = state; // No valid input, keep current state
    endcase

    // Update the state at each clock cycle
    if (state != next_state) begin
      door_open_pulse <= 1'b1; // Generate the pulse
    end else begin
      door_open_pulse <= 1'b0; // No state change, no pulse
    end
    
    state <= next_state; // Assign the next state to the current state
  end
endmodule

ParkingSystem/FSM_tb.v
`timescale 1 ns / 1 ps

module FSM_tb;

  reg clk;
  reg [3:0] in;
  wire [3:0] state;
  wire door_open_pulse;

  FSM UUT (
      .clk(clk),
      .in(in),
      .state(state),
      .door_open_pulse(door_open_pulse)
  );

  initial begin

    $dumpvars(0, FSM_tb);
    $dumpfile("FSM_tb.vcd");
    clk = 0;
    forever #50 clk = ~clk;
  end

  initial begin
    in = 4'b0000;
    #100;

    in = 4'b1000;
    #100;

    in = 4'b0100;
    #100;

    in = 4'b1000;
    #100;

    in = 4'b1000;
    #100;

    in = 4'b1000;
    #100;

    #3000;

    $finish;
  end

endmodule

ParkingSystem/seven_segment_display.v
module seven_segment_display (
    input wire clk,
    input wire [11:0] s1a,
    output reg [7:0] set_Data,
    output reg [4:0] see_sel
);
  reg [ 3:0] digit;
  reg [ 1:0] digit_select;
  reg [21:0] refresh_counter;  // Counter to create a refresh rate

  // Generate a slower clock enable signal for refreshing the display
  always @(posedge clk) begin
    if (refresh_counter[9] == 1) refresh_counter <= 0;
    else refresh_counter <= refresh_counter + 1;
  end

  // Segment definitions for 0-9
  always @(digit) begin
    case (digit)
      4'd0: set_Data = 8'b00111111;
      4'd1: set_Data = 8'b00000110;
      4'd2: set_Data = 8'b01011011;
      4'd3: set_Data = 8'b01001111;
      4'd4: set_Data = 8'b01100110;
      4'd5: set_Data = 8'b01101101;
      4'd6: set_Data = 8'b01111101;
      4'd7: set_Data = 8'b00000111;
      4'd8: set_Data = 8'b01111111;
      4'd9: set_Data = 8'b01101111;
      default: set_Data = 8'b00000000;  // Off
    endcase
  end

  // Multiplexing digits with refresh counter
  always @(posedge clk) begin
    if (refresh_counter[9] == 1) begin
      if (digit_select < 3) digit_select <= digit_select + 1;
      else digit_select <= 0;
      case (digit_select)
        2'b00: begin
          digit   = s1a[2:0];
          see_sel = 5'b01000;  // Select first 7-segment display
        end
        2'b01: begin
          digit   = s1a[5:3];
          see_sel = 5'b00100;  // Select second 7-segment display
        end
        2'b10: begin
          digit   = s1a[8:6];
          see_sel = 5'b00010;  // Select third 7-segment display
        end
        2'b11: begin
          digit   = s1a[11:9];
          see_sel = 5'b00001;  // Select fourth 7-segment display
        end
      endcase
    end
  end
endmodule

ParkingSystem/Capacity.v
module Capacity (
    input [3:0] in,  // 4-bit input data
    output reg [2:0] out  // 3-bit output to store the count of zeros (max 4 zeros)
);

  integer i;  // Loop variable

  always @(*) begin
    out = 0;  // Initialize the count
    for (i = 0; i < 4; i = i + 1) begin
      if (in[i] == 1'b0) begin
        out = out + 1;
      end
    end
  end

endmodule

ParkingSystem/Circuit.v
module Circuit (
    input clk,
    input entry_sensor,
    input exit_sensor,
    input [1:0] switch,
    output [3:0] parking_slots,
    output door_open_light,
    output full_light,
    output [2:0] capacity,
    output [2:0] best_place,
    output [7:0] sev_data,
    output [4:0] sev_sel
);

  wire [3:0] state;
  and (parking_slots[0], 1'b1, state[0]);
  and (parking_slots[1], 1'b1, state[1]);
  and (parking_slots[2], 1'b1, state[2]);
  and (parking_slots[3], 1'b1, state[3]);
  wire full_temp;
  and (full_temp, state[0], state[1], state[2], state[3]);
  and #50 (full_light, full_temp, entry_sensor, ~exit_sensor);

  FSM fsm (
      .clk(clk),
      .in({entry_sensor, exit_sensor, switch}),
      .state(state),
      .door_open_pulse(door_open_light)
  );

  Capacity cap (
      .in (state),
      .out(capacity)
  );

  wire [2:0] temp_cap;
  wire [2:0] temp_loc;


  Location loc (
      .in(state),
      .encoded(best_place)
  );

  and (
      temp_cap[0], 1'b1, capacity[0]
  ), (
      temp_cap[1], 1'b1, capacity[1]
  ), (
      temp_cap[2], 1'b1, capacity[2]
  ), (
      temp_loc[0], 1'b1, best_place[0]
  ), (
      temp_loc[1], 1'b1, best_place[1]
  ), (
      temp_loc[2], 1'b1, best_place[2]
  );

seven_segment_display sev_seg (
    .clk(clk),
    .s1a({3'b000, temp_cap, 3'b000, temp_loc}),
    .set_Data(sev_data),
    .see_sel(sev_sel)
);

endmodule

ParkingSystem/Circuit_tb.v
module Circuit_tb;

  reg clk;
  reg entry;
  reg exit;
  reg [1:0] switch;
  wire [3:0] state;
  wire open;
  wire full;
  wire [2:0] capacity;
  wire [2:0] best_place;
  wire [7:0] sev_data;
  wire [4:0] sev_sel;

  integer file;
  integer file_out;
  integer status;

  Circuit UUT (
      .clk(clk),
      .entry_sensor(entry),
      .exit_sensor(exit),
      .switch(switch),
      .parking_slots(state),
      .door_open_light(open),
      .full_light(full),
      .capacity(capacity),
      .best_place(best_place),
      .sev_data(sev_data),
      .sev_sel(sev_sel)
  );

  initial begin
    $dumpfile("Circuit_tb.vcd");
    $dumpvars(0, Circuit_tb);
    entry = 0;
    exit = 0;
    switch = 2'b00;
    clk = 0;

    file = $fopen("input.txt", "r");
    file_out = $fopen("output.txt", "w");
    if (file == 0) begin
      $display("Error: Failed to open file.");
      $finish;
    end

    while (!$feof(
        file
    )) begin
      status = $fscanf(file, "%1b %1b %1b %1b\n", entry, exit, switch[1], switch[0]);
      if (status == 4) begin
        #100;
        $fwrite(file_out, "%b [%d,%d] %0s%0s\n", state, capacity, best_place,
                open ? "Open Door " : "", full ? "Full" : "");


      end else begin
        $display("Error: File format incorrect or incomplete data.");
        $finish;
      end
    end

    $fclose(file);
    $fclose(file_out);

    #200 $finish;
  end

  always begin
    #50;
    clk = ~clk;
  end
endmodule

ParkingSystem/Capacity_tb.v
`timescale 1 ns / 1 ps

module Capacity_tb;

  reg  [3:0] in;
  wire [2:0] out;

  Capacity UUT (
      .in (in),
      .out(out)
  );

  initial begin
    $dumpfile("Capacity_tb.vcd");
    $dumpvars(0, Capacity_tb);

  end

  initial begin
    in = 4'b0001;
    #100;

    in = 4'b0000;
    #100;

    in = 4'b0100;
    #100;

    in = 4'b1010;
    #100;

    in = 4'b1111;
    #100;

    in = 4'b1110;
    #100;

  end

endmodule

ParkingSystem/Capacity_tb.vcd
$date
	Wed Jan 08 15:01:33 2025
$end
$version
	Icarus Verilog
$end
$timescale
	1ps
$end
$scope module Capacity_tb $end
$var wire 3 ! out [2:0] $end
$var reg 4 " in [3:0] $end
$scope module UUT $end
$var wire 4 # in [3:0] $end
$var reg 3 $ out [2:0] $end
$var integer 32 % i [31:0] $end
$upscope $end
$upscope $end
$scope module Circuit_tb $end
$var wire 4 & state [3:0] $end
$var wire 5 ' sev_sel [4:0] $end
$var wire 8 ( sev_data [7:0] $end
$var wire 1 ) open $end
$var wire 1 * full $end
$var wire 3 + capacity [2:0] $end
$var wire 3 , best_place [2:0] $end
$var reg 1 - clk $end
$var reg 1 . entry $end
$var reg 1 / exit $end
$var reg 2 0 switch [1:0] $end
$var integer 32 1 file [31:0] $end
$var integer 32 2 file_out [31:0] $end
$var integer 32 3 status [31:0] $end
$scope module UUT $end
$var wire 1 - clk $end
$var wire 1 . entry_sensor $end
$var wire 1 / exit_sensor $end
$var wire 1 * full_light $end
$var wire 1 4 full_temp $end
$var wire 2 5 switch [1:0] $end
$var wire 3 6 temp_loc [2:0] $end
$var wire 3 7 temp_cap [2:0] $end
$var wire 4 8 state [3:0] $end
$var wire 5 9 sev_sel [4:0] $end
$var wire 8 : sev_data [7:0] $end
$var wire 4 ; parking_slots [3:0] $end
$var wire 1 ) door_open_light $end
$var wire 3 < capacity [2:0] $end
$var wire 3 = best_place [2:0] $end
$scope module cap $end
$var wire 4 > in [3:0] $end
$var reg 3 ? out [2:0] $end
$var integer 32 @ i [31:0] $end
$upscope $end
$scope module fsm $end
$var wire 1 - clk $end
$var wire 4 A in [3:0] $end
$var reg 1 ) door_open_pulse $end
$var reg 4 B next_state [3:0] $end
$var reg 4 C state [3:0] $end
$upscope $end
$scope module loc $end
$var wire 1 D and0 $end
$var wire 1 E and1 $end
$var wire 1 F and2 $end
$var wire 4 G in [3:0] $end
$var wire 1 H not_in0 $end
$var wire 1 I not_in1 $end
$var wire 1 J not_in2 $end
$var wire 1 K not_in3 $end
$var wire 3 L encoded [2:0] $end
$upscope $end
$scope module sev_seg $end
$var wire 1 - clk $end
$var wire 12 M s1a [11:0] $end
$var reg 4 N digit [3:0] $end
$var reg 2 O digit_select [1:0] $end
$var reg 22 P refresh_counter [21:0] $end
$var reg 5 Q see_sel [4:0] $end
$var reg 8 R set_Data [7:0] $end
$upscope $end
$upscope $end
$upscope $end
$scope module FSM_tb $end
$var wire 4 S state [3:0] $end
$var wire 1 T door_open_pulse $end
$var reg 1 U clk $end
$var reg 4 V in [3:0] $end
$scope module UUT $end
$var wire 1 U clk $end
$var wire 4 W in [3:0] $end
$var reg 1 T door_open_pulse $end
$var reg 4 X next_state [3:0] $end
$var reg 4 Y state [3:0] $end
$upscope $end
$upscope $end
$scope module Location_tb $end
$var wire 3 Z encoded [2:0] $end
$var reg 4 [ in [3:0] $end
$scope module UUT $end
$var wire 1 \ and0 $end
$var wire 1 ] and1 $end
$var wire 1 ^ and2 $end
$var wire 4 _ in [3:0] $end
$var wire 1 ` not_in0 $end
$var wire 1 a not_in1 $end
$var wire 1 b not_in2 $end
$var wire 1 c not_in3 $end
$var wire 3 d encoded [2:0] $end
$upscope $end
$upscope $end
$enddefinitions $end
$comment Show the parameter values. $end
$dumpall
$end
#0
$dumpvars
b1 d
1c
1b
1a
0`
b1 _
0^
0]
1\
b1 [
b1 Z
b0 Y
bx X
b0 W
b0 V
0U
0T
b0 S
bx R
bx Q
bx P
bx O
bx N
b100000000 M
b0 L
1K
1J
1I
1H
b0 G
0F
0E
0D
b0 C
bx B
b0 A
b100 @
b100 ?
b0 >
b0 =
b100 <
b0 ;
bx :
bx 9
b0 8
b100 7
b0 6
b0 5
04
b100 3
b10000000000000000000000000000100 2
b10000000000000000000000000000011 1
b0 0
0/
0.
0-
b0 ,
b100 +
x*
0)
bx (
bx '
b0 &
b100 %
b11 $
b1 #
b1 "
b11 !
$end
#50000
b0 X
b0 B
0*
1U
1-
#100000
b0 Z
b0 d
1`
0\
b100 %
b100 !
b100 $
0U
0-
b0 [
b0 _
b1000 V
b1000 W
b1000 A
1.
b0 "
b0 #
#150000
b1 6
b1 ,
b1 =
b1 L
b11000001 M
b11 7
0H
1D
b1 &
b1 ;
b100 @
b11 +
b11 <
b11 ?
b1 S
b1 Y
1T
b1 8
b1 >
b1 C
b1 G
1)
b1 X
b1 B
1U
1-
#200000
0b
b100 %
b11 !
b11 $
0U
0-
b100 [
b100 _
b100 V
b100 W
b1001 A
b1 0
b1 5
b100 "
b100 #
#250000
b10 6
0D
b10 ,
b10 =
b10 L
b10000010 M
b10 7
0I
1E
b11 &
b11 ;
b100 @
b10 +
b10 <
b10 ?
b0 S
b0 Y
b11 8
b11 >
b11 C
b11 G
b0 X
b11 B
1U
1-
#300000
0c
1b
0a
b100 %
b10 !
b10 $
0U
0-
b1010 [
b1010 _
b1000 V
b1000 W
b1 A
0.
b1010 "
b1010 #
#350000
b1 S
b1 Y
0)
b1 X
1U
1-
#400000
0b
0`
0]
b101 Z
b101 d
b100 %
b0 !
b0 $
0U
0-
b1111 [
b1111 _
b11 0
b11 5
b1011 A
1.
b1111 "
b1111 #
#450000
b11 6
0E
b11 ,
b11 =
b11 L
b1000011 M
b1 7
0J
1F
b111 &
b111 ;
b100 @
b1 +
b1 <
b1 ?
b11 S
b11 Y
b111 8
b111 >
b111 C
b111 G
1)
b11 X
b111 B
1U
1-
#500000
1`
b0 Z
b0 d
b1 !
b1 $
b100 %
0U
0-
b1110 [
b1110 _
b1 0
b1 5
1/
b101 A
0.
b1110 "
b1110 #
#550000
b1 6
1D
b1 ,
b1 =
b1 L
b10000001 M
b10 7
1I
0F
b101 &
b101 ;
b100 @
b10 +
b10 <
b10 ?
b111 S
b111 Y
b101 8
b101 >
b101 C
b101 G
b111 X
b101 B
1U
1-
#600000
b11 Z
b11 d
1^
1c
0`
0U
0-
b111 [
b111 _
b0 0
b0 5
0/
b1000 A
1.
#650000
b11 6
0D
b11 ,
b11 =
b11 L
b1000011 M
b1 7
0I
1F
b111 &
b111 ;
b100 @
b1 +
b1 <
b1 ?
b1111 S
b1111 Y
b111 8
b111 >
b111 C
b111 G
b1111 X
b111 B
1U
1-
#700000
0U
0-
1/
b100 A
0.
#750000
b0 6
b0 ,
b0 =
b0 L
b10000000 M
b10 7
1H
0F
b110 &
b110 ;
b100 @
b10 +
b10 <
b10 ?
0T
b110 8
b110 >
b110 C
b110 G
b110 B
1U
1-
#800000
0U
0-
#850000
0)
1U
1-
#900000
0U
0-
b1 0
b1 5
0/
b1001 A
1.
#950000
b11 6
b11 ,
b11 =
b11 L
b1000011 M
b1 7
0H
1F
b111 &
b111 ;
b100 @
b1 +
b1 <
b1 ?
b111 8
b111 >
b111 C
b111 G
1)
b111 B
1U
1-
#1000000
0U
0-
b1000 A
b0 0
b0 5
#1050000
b101 6
0F
b101 M
b0 7
0K
b101 ,
b101 =
b101 L
14
b1111 &
b1111 ;
b100 @
b0 +
b0 <
b0 ?
b1111 8
b1111 >
b1111 C
b1111 G
b1111 B
1U
1-
#1100000
1*
0U
0-
b1011 A
b11 0
b11 5
#1150000
0)
1U
1-
#1200000
0U
0-
b1000 A
b0 0
b0 5
#1250000
1U
1-
#1300000
0U
0-
b0 A
0.
#1350000
0*
1U
1-
#1400000
0U
0-
b100 A
1/
#1450000
b0 6
b1000000 M
b1 7
1H
b0 ,
b0 =
b0 L
04
b1110 &
b1110 ;
b1 +
b1 <
b1 ?
b100 @
b1110 8
b1110 >
b1110 C
b1110 G
1)
b1110 B
1U
1-
#1500000
0U
0-
b11 0
b11 5
b11 A
0/
#1550000
0)
1U
1-
#1600000
0U
0-
b10 0
b10 5
b110 A
1/
#1650000
b10000000 M
b10 7
1J
b1010 &
b1010 ;
b100 @
b10 +
b10 <
b10 ?
b1010 8
b1010 >
b1010 C
b1010 G
1)
b1010 B
1U
1-
#1700000
0U
0-
b111 A
b11 0
b11 5
#1750000
b11000000 M
b11 7
1K
b10 &
b10 ;
b100 @
b11 +
b11 <
b11 ?
b10 8
b10 >
b10 C
b10 G
b10 B
1U
1-
#1800000
0U
0-
b101 A
b1 0
b1 5
#1850000
b100000000 M
b100 7
1I
b0 &
b0 ;
b100 @
b100 +
b100 <
b100 ?
b0 8
b0 >
b0 C
b0 G
b0 B
1U
1-
#1900000
0U
0-
b0 0
b0 5
b0 A
0/
#1950000
0)
1U
1-
