ParkingSystem/Location.v
// The module returns the first 0 it founds in input.
// if there is any park it returns index. 0 to 3

// And if there isn't any park spot, full state, it returns 5. 101

module Location (
    input  wire [3:0] in,
    output wire [2:0] encoded
);

  wire not_in3, not_in2, not_in1, not_in0;
  wire and0, and1, and2;


  not U0 (not_in3, in[3]);
  not U1 (not_in2, in[2]);
  not U2 (not_in1, in[1]);
  not U3 (not_in0, in[0]);

  and U4 (and0, not_in1, in[0]);
  and U5 (and1, not_in2, in[1], in[0]);
  and U6 (and2, not_in3, in[2], in[1], in[0]);

  and U7 (encoded[2], in[3], in[2], in[1], in[0]);


  or U8 (encoded[1], and2, and1);
  or U9 (encoded[0], encoded[2], and2, and0);


endmodule

ParkingSystem/Capacity.v
module Capacity (
    input [3:0] in,  // 4-bit input data
    output reg [2:0] out  // 3-bit output to store the count of zeros (max 4 zeros)
);

  integer i;  // Loop variable

  always @(*) begin
    out = 0;  // Initialize the count
    for (i = 0; i < 4; i = i + 1) begin
      if (in[i] == 1'b0) begin
        out = out + 1;
      end
    end
  end

endmodule

ParkingSystem/FSM.v
module FSM (
    input  wire       clk,             // Clock signal
    input  wire [3:0] in,              // 4-bit input: {EnterSensor, ExitSensor, ExitPlace[1:0]}
    output reg  [3:0] state,           // 4-bit state representing the parking spots
    output reg        door_open_pulse  // Pulse for door open LED
);

  // Initialization
  initial begin
    state           = 4'b0000;  // Initial state: all parking spots empty
    door_open_pulse = 1'b0;     // Door open LED initially off
  end

reg [3:0] next_state; // Internal signal to store the next state

  always @(posedge clk) begin
    next_state = state;   // Default next state is the current state

    case (in[3:2])  // Check the input format
      2'b10: begin  // Enter sensor triggered, Exit sensor not triggered
        if (state != 4'b1111) begin  // Parking not full
          // Find the first empty parking spot (rightmost 0 becomes 1)
          case (state)
            4'b0000: next_state = 4'b0001;
            4'b0001: next_state = 4'b0011;
            4'b0010: next_state = 4'b0011;
            4'b0011: next_state = 4'b0111;
            4'b0100: next_state = 4'b0101;
            4'b0101: next_state = 4'b0111;
            4'b0110: next_state = 4'b0111;
            4'b0111: next_state = 4'b1111;
            4'b1000: next_state = 4'b1001;
            4'b1001: next_state = 4'b1011;
            4'b1010: next_state = 4'b1011;
            4'b1011: next_state = 4'b1111;
            4'b1100: next_state = 4'b1101;
            4'b1101: next_state = 4'b1111;
            4'b1110: next_state = 4'b1111;
            default: next_state = state; // Default to current state
          endcase
        end
      end

      2'b01: begin  // Exit sensor triggered, Enter sensor not triggered
        // Check the exit place validity and remove the car
        case (in[1:0])  // ExitPlace
          2'b00: if (state[0]) next_state = state & 4'b1110;  // Exit from spot 0
          2'b01: if (state[1]) next_state = state & 4'b1101;  // Exit from spot 1
          2'b10: if (state[2]) next_state = state & 4'b1011;  // Exit from spot 2
          2'b11: if (state[3]) next_state = state & 4'b0111;  // Exit from spot 3
          default: next_state = state; // Invalid exit place, keep current state
        endcase
      end

      default: next_state = state; // No valid input, keep current state
    endcase

    // Update the state at each clock cycle
    if (state != next_state) begin
      door_open_pulse <= 1'b1; // Generate the pulse
    end else begin
      door_open_pulse <= 1'b0; // No state change, no pulse
    end
    
    state <= next_state; // Assign the next state to the current state
  end
endmodule

ParkingSystem/Circuit.v
module Circuit (
    input clk,
    input entry_sensor,
    input exit_sensor,
    input [1:0] switch,
    output [3:0] parking_slots,
    output door_open_light,
    output full_light,
    output [2:0] capacity,
    output [2:0] best_place
);

  wire [3:0] state;
  and (parking_slots[0], 1'b1, state[0]);
  and (parking_slots[1], 1'b1, state[1]);
  and (parking_slots[2], 1'b1, state[2]);
  and (parking_slots[3], 1'b1, state[3]);
  wire full_temp;
  and (full_temp, state[0], state[1], state[2], state[3]);
  and #50 (full_light, full_temp, entry_sensor, ~exit_sensor);

  FSM fsm (
      .clk(clk),
      .in({entry_sensor, exit_sensor, switch}),
      .state(state),
      .door_open_pulse(door_open_light)
  );

  Capacity cap (
      .in (state),
      .out(capacity)
  );

  Location loc (
      .in(state),
      .encoded(best_place)
  );

endmodule

ParkingSystem/ReadWrite_tb.v
module ReadWrite_tb;

  reg clk;
  reg entry;
  reg exit;
  reg [1:0] switch;
  wire [3:0] state;
  wire open;
  wire full;
  wire [2:0] capacity;
  wire [2:0] best_place;

  integer file;
  integer file_out;
  integer status;

  Circuit UUT (
      .clk(clk),
      .entry_sensor(entry),
      .exit_sensor(exit),
      .switch(switch),
      .parking_slots(state),
      .door_open_light(open),
      .full_light(full),
      .capacity(capacity),
      .best_place(best_place)
  );

  initial begin
    $dumpfile("ReadWrite_tb.vcd");
    $dumpvars(0, ReadWrite_tb);
    entry = 0;
    exit = 0;
    switch = 2'b00;
    clk = 0;

    file = $fopen("input.txt", "r");
    file_out = $fopen("output.txt", "w");
    if (file == 0) begin
      $display("Error: Failed to open file.");
      $finish;
    end

    while (!$feof(file)) begin
      status = $fscanf(file, "%1b %1b %1b %1b\n", entry, exit, switch[1], switch[0]);
      if (status == 4) begin
        #100;
        $fwrite(file_out, "%b [%d,%d] %s%s\n", state, capacity, best_place,
                open ? "Open Door " : "", full ? "Full" : "");


      end else begin
        $display("Error: File format incorrect or incomplete data.");
        $finish;
      end
    end

    $fclose(file);
    $fclose(file_out);

    #200 $finish;
  end

  always begin
    #50;
    clk = ~clk;
  end
endmodule

ParkingSystem/Location_tb.v
`timescale 1 ns / 1 ps

module Location_tb;

  reg  [3:0] in;
  wire [2:0] encoded;

  Location UUT (
      .in (in),
      .encoded(encoded)
  );

  initial begin
    $dumpfile("Location_tb.vcd");
    $dumpvars(0, Location_tb);

  end

  initial begin
    in = 4'b0001;
    #100;

    in = 4'b0000;
    #100;

    in = 4'b0100;
    #100;

    in = 4'b1010;
    #100;

    in = 4'b1111;
    #100;

    in = 4'b1110;
    #100;

    in = 4'b0111;
    #100;

  end

endmodule

ParkingSystem/Full_Light.v
module Full_Light (
    input  wire [3:0] fsm_state,     // 4-bit FSM state
    input  wire       enter_sensor,  // Enter sensor signal
    input  wire       exit_sensor,   // Exit sensor signal
    input  wire       clk,           // Clock signal for edge detection
    output reg        pulse          // Output pulse
);

  // Initialize outputs and internal signals
  initial begin
    pulse = 0;
  end

  // Internal register to detect the posedge of enter_sensor
  reg enter_sensor_prev;

  always @(posedge clk) begin
    // Edge detection and pulse generation
    if ((fsm_state == 4'b1111) &&  // FSM state is 15 (full parking lot)
        (exit_sensor == 0) &&  // Exit sensor is not active
        (enter_sensor == 1) &&  // Enter sensor is active
        (enter_sensor_prev == 0)) begin  // Detect rising edge of enter_sensor
      pulse <= 1;  // Generate a pulse
    end else begin
      pulse <= 0;  // Reset the pulse
    end

    // Update the previous state of enter_sensor
    enter_sensor_prev <= enter_sensor;
  end

endmodule

ParkingSystem/Full_Light_tb.v
`timescale 1 ns / 1 ps

module Full_Light_tb;

  reg [3:0] in;
  reg ent;
  reg ext;
  reg clk;
  wire pulse;

  Full_Light UUT (
      .fsm_state(in),
      .enter_sensor(ent),
      .exit_sensor(ext),
      .clk(clk),
      .pulse(pulse)
  );

  initial begin
    $dumpfile("Full_Light_tb.vcd");
    $dumpvars(0, Full_Light_tb);
    clk = 0;
    forever #50 clk = ~clk;
  end

  initial begin
    in  = 4'b0001;
    ent = 0;
    ext = 0;
    #100;

    in  = 4'b0000;
    ent = 1;
    ext = 0;
    #100;

    in  = 4'b1111;
    ent = 1;
    ext = 0;
    #100;

    in  = 4'b1010;
    ent = 1;
    ext = 0;
    #100;

    in  = 4'b1111;
    ent = 1;
    ext = 0;
    #100;

    in  = 4'b1111;
    ent = 0;
    ext = 0;
    #100;

    in  = 4'b1111;
    ent = 1;
    ext = 0;
    #100;

    in  = 4'b1100;
    ent = 1;
    ext = 0;
    #100;

    in  = 4'b1101;
    ent = 0;
    ext = 0;
    #100;

    in  = 4'b1111;
    ent = 1;
    ext = 0;
    #100;

  end

endmodule

ParkingSystem/FSM_tb.v
`timescale 1 ns / 1 ps

module FSM_tb;

  reg clk;
  reg [3:0] in;
  wire [3:0] state;
  wire door_open_pulse;

  FSM UUT (
      .clk(clk),
      .in(in),
      .state(state),
      .door_open_pulse(door_open_pulse)
  );

  initial begin

    $dumpvars(0, FSM_tb);
    $dumpfile("FSM_tb.vcd");
    clk = 0;
    forever #50 clk = ~clk;
  end

  initial begin
    in = 4'b0000;
    #100;

    in = 4'b1000;
    #100;

    in = 4'b0100;
    #100;

    in = 4'b1000;
    #100;

    in = 4'b1000;
    #100;

    in = 4'b1000;
    #100;

    #3000;

    $finish;
  end

endmodule

ParkingSystem/Capacity_tb.v
`timescale 1 ns / 1 ps

module Capacity_tb;

  reg  [3:0] in;
  wire [2:0] out;

  Capacity UUT (
      .in (in),
      .out(out)
  );

  initial begin
    $dumpfile("Capacity_tb.vcd");
    $dumpvars(0, Capacity_tb);

  end

  initial begin
    in = 4'b0001;
    #100;

    in = 4'b0000;
    #100;

    in = 4'b0100;
    #100;

    in = 4'b1010;
    #100;

    in = 4'b1111;
    #100;

    in = 4'b1110;
    #100;

  end

endmodule

ParkingSystem/Capacity_tb.vcd
$date
	Fri Dec 27 23:52:52 2024
$end
$version
	Icarus Verilog
$end
$timescale
	1ps
$end
$scope module Capacity_tb $end
$var wire 3 ! out [2:0] $end
$var reg 4 " in [3:0] $end
$scope module UUT $end
$var wire 4 # in [3:0] $end
$var reg 3 $ out [2:0] $end
$var integer 32 % i [31:0] $end
$upscope $end
$upscope $end
$scope module FSM_tb $end
$var wire 4 & state [3:0] $end
$var wire 1 ' door_open_pulse $end
$var reg 1 ( clk $end
$var reg 4 ) in [3:0] $end
$scope module UUT $end
$var wire 1 ( clk $end
$var wire 4 * in [3:0] $end
$var reg 1 ' door_open_pulse $end
$var reg 4 + next_state [3:0] $end
$var reg 4 , state [3:0] $end
$upscope $end
$upscope $end
$scope module Full_Light_tb $end
$var wire 1 - pulse $end
$var reg 1 . clk $end
$var reg 1 / ent $end
$var reg 1 0 ext $end
$var reg 4 1 in [3:0] $end
$scope module UUT $end
$var wire 1 . clk $end
$var wire 1 / enter_sensor $end
$var wire 1 0 exit_sensor $end
$var wire 4 2 fsm_state [3:0] $end
$var reg 1 3 enter_sensor_prev $end
$var reg 1 - pulse $end
$upscope $end
$upscope $end
$scope module Location_tb $end
$var wire 3 4 encoded [2:0] $end
$var reg 4 5 in [3:0] $end
$scope module UUT $end
$var wire 1 6 and0 $end
$var wire 1 7 and1 $end
$var wire 1 8 and2 $end
$var wire 4 9 in [3:0] $end
$var wire 1 : not_in0 $end
$var wire 1 ; not_in1 $end
$var wire 1 < not_in2 $end
$var wire 1 = not_in3 $end
$var wire 3 > encoded [2:0] $end
$upscope $end
$upscope $end
$scope module ReadWrite_tb $end
$var wire 4 ? state [3:0] $end
$var wire 1 @ open $end
$var wire 1 A full $end
$var wire 3 B capacity [2:0] $end
$var wire 3 C best_place [2:0] $end
$var reg 1 D clk $end
$var reg 1 E entry $end
$var reg 1 F exit $end
$var reg 2 G switch [1:0] $end
$var integer 32 H file [31:0] $end
$var integer 32 I file_out [31:0] $end
$var integer 32 J status [31:0] $end
$scope module UUT $end
$var wire 1 D clk $end
$var wire 1 E entry_sensor $end
$var wire 1 F exit_sensor $end
$var wire 1 A full_light $end
$var wire 1 K full_temp $end
$var wire 2 L switch [1:0] $end
$var wire 4 M state [3:0] $end
$var wire 4 N parking_slots [3:0] $end
$var wire 1 @ door_open_light $end
$var wire 3 O capacity [2:0] $end
$var wire 3 P best_place [2:0] $end
$scope module cap $end
$var wire 4 Q in [3:0] $end
$var reg 3 R out [2:0] $end
$var integer 32 S i [31:0] $end
$upscope $end
$scope module fsm $end
$var wire 1 D clk $end
$var wire 4 T in [3:0] $end
$var reg 1 @ door_open_pulse $end
$var reg 4 U next_state [3:0] $end
$var reg 4 V state [3:0] $end
$upscope $end
$scope module loc $end
$var wire 1 W and0 $end
$var wire 1 X and1 $end
$var wire 1 Y and2 $end
$var wire 4 Z in [3:0] $end
$var wire 1 [ not_in0 $end
$var wire 1 \ not_in1 $end
$var wire 1 ] not_in2 $end
$var wire 1 ^ not_in3 $end
$var wire 3 _ encoded [2:0] $end
$upscope $end
$upscope $end
$upscope $end
$enddefinitions $end
$comment Show the parameter values. $end
$dumpall
$end
#0
$dumpvars
b0 _
1^
1]
1\
1[
b0 Z
0Y
0X
0W
b0 V
bx U
b0 T
b100 S
b100 R
b0 Q
b0 P
b100 O
b0 N
b0 M
b0 L
0K
b100 J
b10000000000000000000000000000100 I
b10000000000000000000000000000011 H
b0 G
0F
0E
0D
b0 C
b100 B
xA
0@
b0 ?
b1 >
1=
1<
1;
0:
b1 9
08
07
16
b1 5
b1 4
03
b1 2
b1 1
00
0/
0.
0-
b0 ,
bx +
b0 *
b0 )
0(
0'
b0 &
b100 %
b11 $
b1 #
b1 "
b11 !
$end
#50000
b0 U
b0 +
0A
1D
1.
1(
#100000
b0 4
b0 >
1:
06
b100 %
b100 !
b100 $
0D
0.
0(
b1000 T
1E
b0 5
b0 9
1/
b0 1
b0 2
b1000 )
b1000 *
b0 "
b0 #
#150000
b1 C
b1 P
b1 _
0[
1W
b1 ?
b1 N
b100 S
b11 B
b11 O
b11 R
b1 M
b1 Q
b1 V
b1 Z
1@
13
b1 &
b1 ,
1'
b1 U
b1 +
1D
1.
1(
#200000
0<
b100 %
b11 !
b11 $
0D
0.
0(
b1001 T
b1 G
b1 L
b100 5
b100 9
b1111 1
b1111 2
b100 )
b100 *
b100 "
b100 #
#250000
0W
b10 C
b10 P
b10 _
0\
1X
b11 ?
b11 N
b100 S
b10 B
b10 O
b10 R
b11 M
b11 Q
b11 V
b11 Z
b0 &
b0 ,
b11 U
b0 +
1D
1.
1(
#300000
0=
1<
0;
b100 %
b10 !
b10 $
0D
0.
0(
b1 T
0E
b1010 5
b1010 9
b1010 1
b1010 2
b1000 )
b1000 *
b1010 "
b1010 #
#350000
0@
b1 &
b1 ,
b1 +
1D
1.
1(
#400000
0<
0:
07
b101 4
b101 >
b100 %
b0 !
b0 $
0D
0.
0(
b11 G
b11 L
b1011 T
1E
b1111 5
b1111 9
b1111 1
b1111 2
b1111 "
b1111 #
#450000
0X
b11 C
b11 P
b11 _
0]
1Y
b111 ?
b111 N
b100 S
b1 B
b1 O
b1 R
b111 M
b111 Q
b111 V
b111 Z
1@
b11 &
b11 ,
b111 U
b11 +
1D
1.
1(
#500000
1:
b0 4
b0 >
b1 !
b1 $
b100 %
0D
0.
0(
b1 G
b1 L
1F
b101 T
0E
b1110 5
b1110 9
0/
b1110 "
b1110 #
#550000
1W
b1 C
b1 P
b1 _
1\
0Y
b101 ?
b101 N
b100 S
b10 B
b10 O
b10 R
b101 M
b101 Q
b101 V
b101 Z
03
b111 &
b111 ,
b101 U
b111 +
1D
1.
1(
#600000
b11 4
b11 >
18
1=
0:
0D
0.
0(
b0 G
b0 L
0F
b1000 T
1E
b111 5
b111 9
1/
#650000
0W
b11 C
b11 P
b11 _
0\
1Y
b111 ?
b111 N
b100 S
b1 B
b1 O
b1 R
b111 M
b111 Q
b111 V
b111 Z
13
1-
b1111 &
b1111 ,
b111 U
b1111 +
1D
1.
1(
#700000
0D
0.
0(
1F
b100 T
0E
b1100 1
b1100 2
#750000
b0 C
b0 P
b0 _
1[
0Y
b110 ?
b110 N
b100 S
b10 B
b10 O
b10 R
b110 M
b110 Q
b110 V
b110 Z
0-
0'
b110 U
1D
1.
1(
#800000
0D
0.
0(
0/
b1101 1
b1101 2
#850000
0@
03
1D
1.
1(
#900000
0D
0.
0(
b1 G
b1 L
0F
b1001 T
1E
1/
b1111 1
b1111 2
#950000
b11 C
b11 P
b11 _
0[
1Y
b111 ?
b111 N
b100 S
b1 B
b1 O
b1 R
b111 M
b111 Q
b111 V
b111 Z
1@
13
1-
b111 U
1D
1.
1(
#1000000
0D
0.
0(
b1000 T
b0 G
b0 L
#1050000
0Y
0^
b101 C
b101 P
b101 _
1K
b1111 ?
b1111 N
b100 S
b0 B
b0 O
b0 R
b1111 M
b1111 Q
b1111 V
b1111 Z
0-
b1111 U
1D
1.
1(
#1100000
1A
0D
0.
0(
b1011 T
b11 G
b11 L
#1150000
0@
1D
1.
1(
#1200000
0D
0.
0(
b1000 T
b0 G
b0 L
#1250000
1D
1.
1(
#1300000
0D
0.
0(
b0 T
0E
#1350000
0A
1D
1.
1(
#1400000
0D
0.
0(
b100 T
1F
#1450000
1[
b0 C
b0 P
b0 _
0K
b1110 ?
b1110 N
b1 B
b1 O
b1 R
b100 S
b1110 M
b1110 Q
b1110 V
b1110 Z
1@
b1110 U
1D
1.
1(
#1500000
0D
0.
0(
b11 G
b11 L
b11 T
0F
#1550000
0@
1D
1.
1(
#1600000
0D
0.
0(
b10 G
b10 L
b110 T
1F
#1650000
1]
b1010 ?
b1010 N
b100 S
b10 B
b10 O
b10 R
b1010 M
b1010 Q
b1010 V
b1010 Z
1@
b1010 U
1D
1.
1(
#1700000
0D
0.
0(
b111 T
b11 G
b11 L
#1750000
1^
b10 ?
b10 N
b100 S
b11 B
b11 O
b11 R
b10 M
b10 Q
b10 V
b10 Z
b10 U
1D
1.
1(
#1800000
0D
0.
0(
b101 T
b1 G
b1 L
#1850000
1\
b0 ?
b0 N
b100 S
b100 B
b100 O
b100 R
b0 M
b0 Q
b0 V
b0 Z
b0 U
1D
1.
1(
#1900000
0D
0.
0(
b0 G
b0 L
b0 T
0F
#1950000
0@
1D
1.
1(
