ParkingSystem/Location.v
// The module returns the first 0 it founds in input.
// if there is any park it returns index. 0 to 3

// And if there isn't any park spot, full state, it returns 5. 101

module Location (
    input  wire [3:0] in,
    output wire [2:0] encoded
);

  wire not_in3, not_in2, not_in1, not_in0;
  wire and0, and1, and2;


  not U0 (not_in3, in[3]);
  not U1 (not_in2, in[2]);
  not U2 (not_in1, in[1]);
  not U3 (not_in0, in[0]);

  and U4 (and0, not_in1, in[0]);
  and U5 (and1, not_in2, in[1], in[0]);
  and U6 (and2, not_in3, in[2], in[1], in[0]);

  and U7 (encoded[2], in[3], in[2], in[1], in[0]);


  or U8 (encoded[1], and2, and1);
  or U9 (encoded[0], encoded[2], and2, and0);


endmodule

ParkingSystem/Location_tb.v
`timescale 1 ns / 1 ps

module Location_tb;

  reg  [3:0] in;
  wire [2:0] encoded;

  Location UUT (
      .in (in),
      .encoded(encoded)
  );

  initial begin
    $dumpfile("Location_tb.vcd");
    $dumpvars(0, Location_tb);

  end

  initial begin
    in = 4'b0001;
    #100;

    in = 4'b0000;
    #100;

    in = 4'b0100;
    #100;

    in = 4'b1010;
    #100;

    in = 4'b1111;
    #100;

    in = 4'b1110;
    #100;

    in = 4'b0111;
    #100;

  end

endmodule

ParkingSystem/FSM.v
module FSM (
    input  wire       clk,             // Clock signal
    input  wire [3:0] in,              // 4-bit input: {EnterSensor, ExitSensor, ExitPlace[1:0]}
    input reset,
    output reg  [3:0] state,           // 4-bit state representing the parking spots
    output reg        door_open_pulse  // Pulse for door open LED
);

  // Initialization
  initial begin
    state           = 4'b0000;  // Initial state: all parking spots empty
    door_open_pulse = 1'b0;     // Door open LED initially off
  end

reg [3:0] next_state; // Internal signal to store the next state

  always @(posedge clk or posedge reset) begin
    if (reset) begin
      state = 4'b0000;
    end else begin

      next_state = state;   // Default next state is the current state

      case (in[3:2])  // Check the input format
        2'b10: begin  // Enter sensor triggered, Exit sensor not triggered
          if (state != 4'b1111) begin  // Parking not full
            // Find the first empty parking spot (rightmost 0 becomes 1)
            case (state)
              4'b0000: next_state = 4'b0001;
              4'b0001: next_state = 4'b0011;
              4'b0010: next_state = 4'b0011;
              4'b0011: next_state = 4'b0111;
              4'b0100: next_state = 4'b0101;
              4'b0101: next_state = 4'b0111;
              4'b0110: next_state = 4'b0111;
              4'b0111: next_state = 4'b1111;
              4'b1000: next_state = 4'b1001;
              4'b1001: next_state = 4'b1011;
              4'b1010: next_state = 4'b1011;
              4'b1011: next_state = 4'b1111;
              4'b1100: next_state = 4'b1101;
              4'b1101: next_state = 4'b1111;
              4'b1110: next_state = 4'b1111;
              default: next_state = state; // Default to current state
            endcase
          end
        end

        2'b01: begin  // Exit sensor triggered, Enter sensor not triggered
          // Check the exit place validity and remove the car
          case (in[1:0])  // ExitPlace
            2'b00: if (state[0]) next_state = state & 4'b1110;  // Exit from spot 0
            2'b01: if (state[1]) next_state = state & 4'b1101;  // Exit from spot 1
            2'b10: if (state[2]) next_state = state & 4'b1011;  // Exit from spot 2
            2'b11: if (state[3]) next_state = state & 4'b0111;  // Exit from spot 3
            default: next_state = state; // Invalid exit place, keep current state
          endcase
        end

        default: next_state = state; // No valid input, keep current state
      endcase

      // Update the state at each clock cycle
      if (state != next_state) begin
        door_open_pulse <= 1'b1; // Generate the pulse
      end else begin
        door_open_pulse <= 1'b0; // No state change, no pulse
      end
      
      state <= next_state; // Assign the next state to the current state
    end
    
  end
endmodule

ParkingSystem/FSM_tb.v
`timescale 1 ns / 1 ps

module FSM_tb;

  reg clk;
  reg [3:0] in;
  wire [3:0] state;
  wire door_open_pulse;

  FSM UUT (
      .clk(clk),
      .in(in),
      .state(state),
      .door_open_pulse(door_open_pulse)
  );

  initial begin

    $dumpvars(0, FSM_tb);
    $dumpfile("FSM_tb.vcd");
    clk = 0;
    forever #50 clk = ~clk;
  end

  initial begin
    in = 4'b0000;
    #100;

    in = 4'b1000;
    #100;

    in = 4'b0100;
    #100;

    in = 4'b1000;
    #100;

    in = 4'b1000;
    #100;

    in = 4'b1000;
    #100;

    #3000;

    $finish;
  end

endmodule

ParkingSystem/seven_segment_display.v
module seven_segment_display (
    input wire clk,
    input wire [11:0] s1a,
    output reg [7:0] set_Data,
    output reg [4:0] see_sel
);
  reg [ 2:0] digit;
  reg [ 1:0] digit_select;
  reg [21:0] refresh_counter;  // Counter to create a refresh rate
  
  initial begin
    set_Data = 0;
	 see_sel = 0;
	 digit_select = 0;
	 refresh_counter = 0;
  end

  // Generate a slower clock enable signal for refreshing the display
  always @(posedge clk) begin
    if (refresh_counter[9] == 1) refresh_counter <= 0;
    else refresh_counter <= refresh_counter + 1;
  end

  // Segment definitions for 0-9
  always @(digit) begin
    case (digit)
      3'd0: set_Data = 8'b00111111;
      3'd1: set_Data = 8'b00000110;
      3'd2: set_Data = 8'b01011011;
      3'd3: set_Data = 8'b01001111;
      3'd4: set_Data = 8'b01100110;
      3'd5: set_Data = 8'b01101101;
      default: set_Data = 8'b00000000;  // Off
    endcase
  end

  // Multiplexing digits with refresh counter
  always @(posedge clk) begin
    if (refresh_counter[9] == 1) begin
      if (digit_select < 3) digit_select <= digit_select + 1;
      else digit_select <= 0;
      case (digit_select)
        2'b00: begin
          digit   = 6;
          see_sel = 5'b01000;  // Select first 7-segment display
        end
        2'b01: begin
          digit   = s1a[8:6];
          see_sel = 5'b00100;  // Select second 7-segment display
        end
        2'b10: begin
          digit   = 6;
          see_sel = 5'b00010;  // Select third 7-segment display
        end
        2'b11: begin
          digit   = s1a[2:0];
          see_sel = 5'b00001;  // Select fourth 7-segment display
        end
      endcase
    end
  end
endmodule

ParkingSystem/Capacity.v
module Capacity (
    input [3:0] in,  // 4-bit input data
    output reg [2:0] out  // 3-bit output to store the count of zeros (max 4 zeros)
);

  integer i;  // Loop variable

  always @(*) begin
    out = 0;  // Initialize the count
    for (i = 0; i < 4; i = i + 1) begin
      if (in[i] == 1'b0) begin
        out = out + 1;
      end
    end
  end

endmodule

ParkingSystem/FullLight.v
module FullLight (
    input  wire clk_40MHz,  // 40MHz clock (input trigger detection)
    input  wire clk_1Hz,    // Slow clock (1Hz or 2Hz for flashing)
    input  wire trigger,    // Trigger signal (one 40MHz cycle pulse)
    input  wire reset,      // Asynchronous reset
    output reg  LED         // LED output
);

  initial LED = 0;

  // Parameters for the number of clock cycles to flash
  parameter FLASH_COUNT = 6;

  // Internal state variables
  reg [3:0] counter = 0;  // Counter for flash cycles
  reg       flashing = 0;  // Indicates if flashing is active
  reg       trigger_latched = 0;  // Latches trigger detection at 40MHz

  // Trigger detection logic (using 40MHz clock)
  always @(posedge clk_40MHz or posedge reset) begin
    if (reset) begin
      trigger_latched <= 0;
    end else if (trigger) begin
      trigger_latched <= 1;  // Detect trigger pulse
    end
  end

  // Flashing process (using slow clock)
  always @(posedge clk_1Hz or posedge reset) begin
    if (reset) begin
      // Reset all states
      counter <= 0;
      flashing <= 0;
      LED <= 0;
    end else if (trigger_latched) begin
      // On trigger, start a new flashing process
      counter <= FLASH_COUNT;
      flashing <= 1;
      LED <= 1;
      trigger_latched <= 0;  // Clear the latch once the flashing process starts
    end else if (flashing) begin
      // Continue flashing if active
      if (counter > 1) begin
        counter <= counter - 1;
        LED <= ~LED;  // Toggle LED
      end else begin
        // End flashing process
        counter <= 0;
        flashing <= 0;
        LED <= 0;
      end
    end
  end

endmodule

ParkingSystem/DoorOpen.v
module DoorOpen (
    input  wire clk_40MHz,  // 40MHz clock (input trigger detection)
    input  wire clk_2Hz,    // Slow clock (1Hz or 2Hz for flashing)
    input  wire trigger,    // Trigger signal (one 40MHz cycle pulse)
    input  wire reset,      // Asynchronous reset
    output reg  LED         // LED output
);

  initial LED = 0;

  // Parameters for the number of clock cycles to flash
  parameter FLASH_COUNT = 20;

  // Internal state variables
  reg [3:0] counter = 0;  // Counter for flash cycles
  reg       flashing = 0;  // Indicates if flashing is active
  reg       trigger_latched = 0;  // Latches trigger detection at 40MHz

  // Trigger detection logic (using 40MHz clock)
  always @(posedge clk_40MHz or posedge reset) begin
    if (reset) begin
      trigger_latched <= 0;
    end else if (trigger) begin
      trigger_latched <= 1;  // Detect trigger pulse
    end
  end

  // Flashing process (using slow clock)
  always @(posedge clk_2Hz or posedge reset) begin
    if (reset) begin
      // Reset all states
      counter <= 0;
      flashing <= 0;
      LED <= 0;
    end else if (trigger_latched) begin
      // On trigger, start a new flashing process
      counter <= FLASH_COUNT;
      flashing <= 1;
      LED <= 1;
      trigger_latched <= 0;  // Clear the latch once the flashing process starts
    end else if (flashing) begin
      // Continue flashing if active
      if (counter > 1) begin
        counter <= counter - 1;
        LED <= ~LED;  // Toggle LED
      end else begin
        // End flashing process
        counter <= 0;
        flashing <= 0;
        LED <= 0;
      end
    end
  end

endmodule

ParkingSystem/FrequencyDivider.v
// Frequency Divider Module
module FrequencyDivider (
    input  wire clk_40MHz,      // 40 MHz input clock
    input  wire rst,            // Active-high reset
    output reg  clk_40MHz_out,  // Pass-through of 40 MHz clock
    output reg  clk_100Hz,      // 100 Hz clock output
    output reg  clk_2Hz,        // 2 Hz clock output
    output reg  clk_1Hz         // 1 Hz clock output
);

  // Parameters for frequency division
  parameter DIV_100HZ = 400000;  // 40MHz / 100Hz = 400000
  parameter DIV_2HZ = 20000000;  // 40MHz / 2Hz = 20000000
  parameter DIV_1HZ = 40000000;  // 40MHz / 1Hz = 40000000

  // Counters for each frequency
  reg [31:0] counter_100Hz = 0;
  reg [31:0] counter_2Hz = 0;
  reg [31:0] counter_1Hz = 0;

  // Clock outputs initialization
  initial begin
    clk_40MHz_out = 0;
    clk_100Hz = 0;
    clk_2Hz = 0;
    clk_1Hz = 0;
  end

  always @(posedge clk_40MHz or posedge rst) begin
    if (rst) begin
      // Reset all counters and outputs
      counter_100Hz <= 0;
      counter_2Hz <= 0;
      counter_1Hz <= 0;
      clk_40MHz_out <= 0;
      clk_100Hz <= 0;
      clk_2Hz <= 0;
      clk_1Hz <= 0;
    end else begin
      // Pass-through 40 MHz clock
      clk_40MHz_out <= ~clk_40MHz_out;

      // Generate 100 Hz clock
      if (counter_100Hz == (DIV_100HZ / 2) - 1) begin
        clk_100Hz <= ~clk_100Hz;
        counter_100Hz <= 0;
      end else begin
        counter_100Hz <= counter_100Hz + 1;
      end

      // Generate 2 Hz clock
      if (counter_2Hz == (DIV_2HZ / 2) - 1) begin
        clk_2Hz <= ~clk_2Hz;
        counter_2Hz <= 0;
      end else begin
        counter_2Hz <= counter_2Hz + 1;
      end

      // Generate 1 Hz clock
      if (counter_1Hz == (DIV_1HZ / 2) - 1) begin
        clk_1Hz <= ~clk_1Hz;
        counter_1Hz <= 0;
      end else begin
        counter_1Hz <= counter_1Hz + 1;
      end
    end
  end

endmodule

ParkingSystem/Circuit.v
module Circuit (
    input clk,
    input entry_sensor,
    input exit_sensor,
    input [1:0] switch,
    input reset,

    output [3:0] parking_slots,
    output door_open_light,
    output full_light,
    output [2:0] capacity,
    output [2:0] best_place,
    output [7:0] sev_data,
    output [4:0] sev_sel
);

  wire clk_40MHz, clk_100Hz, clk_2Hz, clk_1Hz;

  FrequencyDivider freqDiv (
      .clk_40MHz(clk),
      .rst(reset),
      .clk_40MHz_out(clk_40MHz),
      .clk_100Hz(clk_100Hz),
      .clk_2Hz(clk_2Hz),
      .clk_1Hz(clk_1Hz)
  );


  wire [3:0] state;
  wire door_open_trigger, full_trigger;

  FSM fsm (
      .clk(clk_40MHz),
      .in({entry_sensor, exit_sensor, switch}),
      .reset(reset),
      .state(state),
      .door_open_pulse(door_open_trigger)
  );

  DoorOpen door_open_flasher (
      .clk_40MHz(clk_40MHz),
      .clk_2Hz(clk_2Hz),
      .trigger(door_open_trigger),
      .reset(reset),
      .LED(door_open_light)
  );

  /*** fix later ***/
  and (parking_slots[0], 1'b1, state[0]);
  and (parking_slots[1], 1'b1, state[1]);
  and (parking_slots[2], 1'b1, state[2]);
  and (parking_slots[3], 1'b1, state[3]);

  /*** fix later ***/
  wire full_temp;
  and (full_temp, state[0], state[1], state[2], state[3]);
  and #50 (full_light, full_temp, entry_sensor, ~exit_sensor);

  FullLight full_light_flasher (
      .clk_40MHz(clk_40MHz),
      .clk_1Hz(clk_1Hz),
      .trigger(full_trigger),
      .reset(reset),
      .LED(full_light)
  );


  wire [2:0] temp_cap;

  Capacity cap (
      .in (state),
      .out(capacity)
  );


  wire [2:0] temp_loc;

  Location loc (
      .in(state),
      .encoded(best_place)
  );

  and (
      temp_cap[0], 1'b1, capacity[0]
  ), (
      temp_cap[1], 1'b1, capacity[1]
  ), (
      temp_cap[2], 1'b1, capacity[2]
  ), (
      temp_loc[0], 1'b1, best_place[0]
  ), (
      temp_loc[1], 1'b1, best_place[1]
  ), (
      temp_loc[2], 1'b1, best_place[2]
  );

  reg [11:0] data;

  always @(*) begin
    // Initialize all bits to avoid 'x'
    data = 12'b0;

    // Assign values to specific bits
    data[2:0] = temp_loc;  // Location information
    data[8:6] = temp_cap;  // Capacity information
  end

  seven_segment_display sev_seg (
      .clk(clk),
      .s1a(data),
      .set_Data(sev_data),
      .see_sel(sev_sel)
  );

endmodule

ParkingSystem/Circuit_tb.v
module Circuit_tb;

  reg clk;
  reg entry;
  reg exit;
  reg [1:0] switch;
  wire [3:0] state;
  wire open;
  wire full;
  wire [2:0] capacity;
  wire [2:0] best_place;
  wire [7:0] sev_data;
  wire [4:0] sev_sel;

  integer file;
  integer file_out;
  integer status;

  Circuit UUT (
      .clk(clk),
      .entry_sensor(entry),
      .exit_sensor(exit),
      .switch(switch),
      .parking_slots(state),
      .door_open_light(open),
      .full_light(full),
      .capacity(capacity),
      .best_place(best_place),
      .sev_data(sev_data),
      .sev_sel(sev_sel)
  );

  initial begin
    $dumpfile("Circuit_tb.vcd");
    $dumpvars(0, Circuit_tb);
    entry = 0;
    exit = 0;
    switch = 2'b00;
    clk = 0;

    file = $fopen("input.txt", "r");
    file_out = $fopen("output.txt", "w");
    if (file == 0) begin
      $display("Error: Failed to open file.");
      $finish;
    end

    while (!$feof(
        file
    )) begin
      status = $fscanf(file, "%1b %1b %1b %1b\n", entry, exit, switch[1], switch[0]);
      if (status == 4) begin
        #100;
        $fwrite(file_out, "%b [%d,%d] %0s%0s\n", state, capacity, best_place,
                open ? "Open Door " : "", full ? "Full" : "");


      end else begin
        $display("Error: File format incorrect or incomplete data.");
        $finish;
      end
    end

    $fclose(file);
    $fclose(file_out);

    #200 $finish;
  end

  always begin
    #50;
    clk = ~clk;
  end
endmodule

ParkingSystem/Capacity_tb.v
`timescale 1 ns / 1 ps

module Capacity_tb;

  reg  [3:0] in;
  wire [2:0] out;

  Capacity UUT (
      .in (in),
      .out(out)
  );

  initial begin
    $dumpfile("Capacity_tb.vcd");
    $dumpvars(0, Capacity_tb);

  end

  initial begin
    in = 4'b0001;
    #100;

    in = 4'b0000;
    #100;

    in = 4'b0100;
    #100;

    in = 4'b1010;
    #100;

    in = 4'b1111;
    #100;

    in = 4'b1110;
    #100;

  end

endmodule

ParkingSystem/Capacity_tb.vcd
$date
	Sat Jan 11 14:56:18 2025
$end
$version
	Icarus Verilog
$end
$timescale
	1ps
$end
$scope module Capacity_tb $end
$var wire 3 ! out [2:0] $end
$var reg 4 " in [3:0] $end
$scope module UUT $end
$var wire 4 # in [3:0] $end
$var reg 3 $ out [2:0] $end
$var integer 32 % i [31:0] $end
$upscope $end
$upscope $end
$scope module Circuit_tb $end
$var wire 4 & state [3:0] $end
$var wire 5 ' sev_sel [4:0] $end
$var wire 8 ( sev_data [7:0] $end
$var wire 1 ) open $end
$var wire 1 * full $end
$var wire 3 + capacity [2:0] $end
$var wire 3 , best_place [2:0] $end
$var reg 1 - clk $end
$var reg 1 . entry $end
$var reg 1 / exit $end
$var reg 2 0 switch [1:0] $end
$var integer 32 1 file [31:0] $end
$var integer 32 2 file_out [31:0] $end
$var integer 32 3 status [31:0] $end
$scope module UUT $end
$var wire 1 - clk $end
$var wire 1 . entry_sensor $end
$var wire 1 / exit_sensor $end
$var wire 1 4 full_temp $end
$var wire 1 5 full_trigger $end
$var wire 1 6 reset $end
$var wire 2 7 switch [1:0] $end
$var wire 3 8 temp_loc [2:0] $end
$var wire 3 9 temp_cap [2:0] $end
$var wire 4 : state [3:0] $end
$var wire 5 ; sev_sel [4:0] $end
$var wire 8 < sev_data [7:0] $end
$var wire 4 = parking_slots [3:0] $end
$var wire 1 * full_light $end
$var wire 1 > door_open_trigger $end
$var wire 1 ) door_open_light $end
$var wire 1 ? clk_40MHz $end
$var wire 1 @ clk_2Hz $end
$var wire 1 A clk_1Hz $end
$var wire 1 B clk_100Hz $end
$var wire 3 C capacity [2:0] $end
$var wire 3 D best_place [2:0] $end
$var reg 12 E data [11:0] $end
$scope module cap $end
$var wire 4 F in [3:0] $end
$var reg 3 G out [2:0] $end
$var integer 32 H i [31:0] $end
$upscope $end
$scope module door_open_flasher $end
$var wire 1 6 reset $end
$var wire 1 > trigger $end
$var wire 1 ? clk_40MHz $end
$var wire 1 @ clk_2Hz $end
$var reg 1 ) LED $end
$var reg 4 I counter [3:0] $end
$var reg 1 J flashing $end
$var reg 1 K trigger_latched $end
$var integer 32 L FLASH_COUNT [31:0] $end
$upscope $end
$scope module freqDiv $end
$var wire 1 - clk_40MHz $end
$var wire 1 6 rst $end
$var reg 1 B clk_100Hz $end
$var reg 1 A clk_1Hz $end
$var reg 1 @ clk_2Hz $end
$var reg 1 ? clk_40MHz_out $end
$var reg 32 M counter_100Hz [31:0] $end
$var reg 32 N counter_1Hz [31:0] $end
$var reg 32 O counter_2Hz [31:0] $end
$var integer 32 P DIV_100HZ [31:0] $end
$var integer 32 Q DIV_1HZ [31:0] $end
$var integer 32 R DIV_2HZ [31:0] $end
$upscope $end
$scope module fsm $end
$var wire 1 ? clk $end
$var wire 4 S in [3:0] $end
$var wire 1 6 reset $end
$var reg 1 > door_open_pulse $end
$var reg 4 T next_state [3:0] $end
$var reg 4 U state [3:0] $end
$upscope $end
$scope module full_light_flasher $end
$var wire 1 A clk_1Hz $end
$var wire 1 ? clk_40MHz $end
$var wire 1 6 reset $end
$var wire 1 5 trigger $end
$var reg 1 * LED $end
$var reg 4 V counter [3:0] $end
$var reg 1 W flashing $end
$var reg 1 X trigger_latched $end
$var integer 32 Y FLASH_COUNT [31:0] $end
$upscope $end
$scope module loc $end
$var wire 1 Z and0 $end
$var wire 1 [ and1 $end
$var wire 1 \ and2 $end
$var wire 4 ] in [3:0] $end
$var wire 1 ^ not_in0 $end
$var wire 1 _ not_in1 $end
$var wire 1 ` not_in2 $end
$var wire 1 a not_in3 $end
$var wire 3 b encoded [2:0] $end
$upscope $end
$scope module sev_seg $end
$var wire 1 - clk $end
$var wire 12 c s1a [11:0] $end
$var reg 3 d digit [2:0] $end
$var reg 2 e digit_select [1:0] $end
$var reg 22 f refresh_counter [21:0] $end
$var reg 5 g see_sel [4:0] $end
$var reg 8 h set_Data [7:0] $end
$upscope $end
$upscope $end
$upscope $end
$scope module FSM_tb $end
$var wire 4 i state [3:0] $end
$var wire 1 j door_open_pulse $end
$var reg 1 k clk $end
$var reg 4 l in [3:0] $end
$scope module UUT $end
$var wire 1 k clk $end
$var wire 4 m in [3:0] $end
$var wire 1 n reset $end
$var reg 1 j door_open_pulse $end
$var reg 4 o next_state [3:0] $end
$var reg 4 p state [3:0] $end
$upscope $end
$upscope $end
$scope module Location_tb $end
$var wire 3 q encoded [2:0] $end
$var reg 4 r in [3:0] $end
$scope module UUT $end
$var wire 1 s and0 $end
$var wire 1 t and1 $end
$var wire 1 u and2 $end
$var wire 4 v in [3:0] $end
$var wire 1 w not_in0 $end
$var wire 1 x not_in1 $end
$var wire 1 y not_in2 $end
$var wire 1 z not_in3 $end
$var wire 3 { encoded [2:0] $end
$upscope $end
$upscope $end
$enddefinitions $end
$comment Show the parameter values. $end
$dumpall
$end
#0
$dumpvars
b1 {
1z
1y
1x
0w
b1 v
0u
0t
1s
b1 r
b1 q
b0 p
bx o
zn
b0 m
b0 l
0k
0j
b0 i
bx h
bx g
bx f
bx e
bx d
b100000000 c
b0 b
1a
1`
1_
1^
b0 ]
0\
0[
0Z
b110 Y
0X
0W
b0 V
b0 U
bx T
b0 S
b1001100010010110100000000 R
b10011000100101101000000000 Q
b1100001101010000000 P
b0 O
b0 N
b0 M
b10100 L
0K
0J
b0 I
b100 H
b100 G
b0 F
b100000000 E
b0 D
b100 C
0B
0A
0@
0?
0>
b0 =
bx <
bx ;
b0 :
b100 9
b0 8
b0 7
z6
x5
04
b100 3
b10000000000000000000000000000100 2
b10000000000000000000000000000011 1
b0 0
0/
0.
0-
b0 ,
b100 +
x*
x)
bx (
bx '
b0 &
b100 %
b11 $
b1 #
b1 "
b11 !
$end
#50000
b0 T
b1 N
b1 O
b1 M
1?
b0 o
05
1k
1-
#100000
b0 q
b0 {
1w
0s
b100 %
b100 !
b100 $
0k
0-
b0 r
b0 v
b1000 l
b1000 m
b1000 S
1.
b0 "
b0 #
#150000
b1 i
b1 p
1j
b10 N
b10 O
b10 M
0?
b1 o
1k
1-
#200000
0y
b100 %
b11 !
b11 $
0k
0-
b100 r
b100 v
b100 l
b100 m
b1001 S
b1 0
b1 7
b100 "
b100 #
#250000
b1 8
b11000001 E
b11000001 c
b1 ,
b1 D
b1 b
b11 9
0^
1Z
b1 &
b1 =
b100 H
b11 +
b11 C
b11 G
b1 :
b1 F
b1 U
b1 ]
1>
b1 T
b0 i
b0 p
b11 N
b11 O
b11 M
1?
b0 o
1k
1-
#300000
0z
1y
0x
b100 %
b10 !
b10 $
0k
0-
b1010 r
b1010 v
b1000 l
b1000 m
b1 S
0.
b1010 "
b1010 #
#350000
b1 i
b1 p
b100 N
b100 O
b100 M
0?
b1 o
1k
1-
#400000
0y
0w
0t
b101 q
b101 {
b100 %
b0 !
b0 $
0k
0-
b1111 r
b1111 v
b11 0
b11 7
b1011 S
1.
b1111 "
b1111 #
#450000
b10 8
b10000010 E
b10000010 c
0Z
b10 ,
b10 D
b10 b
b10 9
0_
1[
b11 &
b11 =
b100 H
b10 +
b10 C
b10 G
b11 :
b11 F
b11 U
b11 ]
1K
b11 T
b11 i
b11 p
b101 N
b101 O
b101 M
1?
b11 o
1k
1-
#500000
1w
b0 q
b0 {
b1 !
b1 $
b100 %
0k
0-
b1110 r
b1110 v
b1 0
b1 7
1/
b101 S
0.
b1110 "
b1110 #
#550000
b111 i
b111 p
b110 N
b110 O
b110 M
0?
b111 o
1k
1-
#600000
b11 q
b11 {
1u
1z
0w
0k
0-
b111 r
b111 v
b0 0
b0 7
0/
b1000 S
1.
#650000
b11 8
b1000011 E
b1000011 c
0[
b11 ,
b11 D
b11 b
b1 9
0`
1\
b111 &
b111 =
b100 H
b1 +
b1 C
b1 G
b111 :
b111 F
b111 U
b111 ]
b111 T
b1111 i
b1111 p
b111 N
b111 O
b111 M
1?
b1111 o
1k
1-
#700000
0k
0-
1/
b100 S
0.
#750000
0j
b1000 N
b1000 O
b1000 M
0?
1k
1-
#800000
0k
0-
#850000
b0 8
b10000000 E
b10000000 c
b0 ,
b0 D
b0 b
b10 9
1^
0\
b110 &
b110 =
b100 H
b10 +
b10 C
b10 G
b110 :
b110 F
b110 U
b110 ]
b110 T
b1001 N
b1001 O
b1001 M
1?
1k
1-
#900000
0k
0-
b1 0
b1 7
0/
b1001 S
1.
#950000
b1010 N
b1010 O
b1010 M
0?
1k
1-
#1000000
0k
0-
b1000 S
b0 0
b0 7
#1050000
b11 8
b1000011 E
b1000011 c
b11 ,
b11 D
b11 b
b1 9
0^
1\
b111 &
b111 =
b100 H
b1 +
b1 C
b1 G
b111 :
b111 F
b111 U
b111 ]
b111 T
b1011 N
b1011 O
b1011 M
1?
1k
1-
#1100000
0k
0-
b1011 S
b11 0
b11 7
#1150000
b1100 N
b1100 O
b1100 M
0?
1k
1-
#1200000
0k
0-
b1000 S
b0 0
b0 7
#1250000
b101 8
b101 E
b101 c
0\
b0 9
0a
b101 ,
b101 D
b101 b
14
b1111 &
b1111 =
b100 H
b0 +
b0 C
b0 G
b1111 :
b1111 F
b1111 U
b1111 ]
b1111 T
b1101 N
b1101 O
b1101 M
1?
1k
1-
#1300000
15
0k
0-
b0 S
0.
#1350000
b1110 N
b1110 O
b1110 M
0?
05
1k
1-
#1400000
0k
0-
b100 S
1/
#1450000
b0 8
b1000000 E
b1000000 c
b1 9
1^
b0 ,
b0 D
b0 b
04
b1110 &
b1110 =
b1 +
b1 C
b1 G
b100 H
b1110 :
b1110 F
b1110 U
b1110 ]
b1110 T
b1111 N
b1111 O
b1111 M
1?
1k
1-
#1500000
0k
0-
b11 0
b11 7
b11 S
0/
#1550000
b10000 N
b10000 O
b10000 M
0?
1k
1-
#1600000
0k
0-
b10 0
b10 7
b110 S
1/
#1650000
b10000000 E
b10000000 c
b10 9
1`
b1010 &
b1010 =
b100 H
b10 +
b10 C
b10 G
b1010 :
b1010 F
b1010 U
b1010 ]
b1010 T
b10001 N
b10001 O
b10001 M
1?
1k
1-
#1700000
0k
0-
b111 S
b11 0
b11 7
#1750000
b10010 N
b10010 O
b10010 M
0?
1k
1-
#1800000
0k
0-
b101 S
b1 0
b1 7
#1850000
b11000000 E
b11000000 c
b11 9
1_
b1000 &
b1000 =
b100 H
b11 +
b11 C
b11 G
b1000 :
b1000 F
b1000 U
b1000 ]
b1000 T
b10011 N
b10011 O
b10011 M
1?
1k
1-
#1900000
0k
0-
b0 0
b0 7
b0 S
0/
#1950000
b10100 N
b10100 O
b10100 M
0?
1k
1-
#2000000
0k
0-
#2050000
0>
b10101 N
b10101 O
b10101 M
1?
1k
1-
#2100000
0k
0-
#2150000
b10110 N
b10110 O
b10110 M
0?
1k
1-
