ParkingSystem/Location.v
// The module returns the first 0 it founds in input.
// if there is any park it returns index. 0 to 3

// And if there isn't any park spot, full state, it returns 5. 101

module Location (
    input  wire [3:0] in,
    output wire [2:0] encoded
);

  wire not_in3, not_in2, not_in1, not_in0;
  wire and0, and1, and2;


  not U0 (not_in3, in[3]);
  not U1 (not_in2, in[2]);
  not U2 (not_in1, in[1]);
  not U3 (not_in0, in[0]);

  and U4 (and0, not_in1, in[0]);
  and U5 (and1, not_in2, in[1], in[0]);
  and U6 (and2, not_in3, in[2], in[1], in[0]);

  and U7 (encoded[2], in[3], in[2], in[1], in[0]);


  or U8 (encoded[1], and2, and1);
  or U9 (encoded[0], encoded[2], and2, and0);


endmodule

ParkingSystem/Location_tb.v
`timescale 1 ns / 1 ps

module Location_tb;

  reg  [3:0] in;
  wire [2:0] encoded;

  Location UUT (
      .in (in),
      .encoded(encoded)
  );

  initial begin
    $dumpfile("Location_tb.vcd");
    $dumpvars(0, Location_tb);

  end

  initial begin
    in = 4'b0001;
    #100;

    in = 4'b0000;
    #100;

    in = 4'b0100;
    #100;

    in = 4'b1010;
    #100;

    in = 4'b1111;
    #100;

    in = 4'b1110;
    #100;

    in = 4'b0111;
    #100;

  end

endmodule

ParkingSystem/FSM.v
module FSM (
    input  wire       clk,             // Clock signal
    input  wire [3:0] in,              // 4-bit input: {EnterSensor, ExitSensor, ExitPlace[1:0]}
    output reg  [3:0] state,           // 4-bit state representing the parking spots
    output reg        door_open_pulse  // Pulse for door open LED
);

  // Initialization
  initial begin
    state           = 4'b0000;  // Initial state: all parking spots empty
    door_open_pulse = 1'b0;     // Door open LED initially off
  end

reg [3:0] next_state; // Internal signal to store the next state

  always @(posedge clk) begin
    next_state = state;   // Default next state is the current state

    case (in[3:2])  // Check the input format
      2'b10: begin  // Enter sensor triggered, Exit sensor not triggered
        if (state != 4'b1111) begin  // Parking not full
          // Find the first empty parking spot (rightmost 0 becomes 1)
          case (state)
            4'b0000: next_state = 4'b0001;
            4'b0001: next_state = 4'b0011;
            4'b0010: next_state = 4'b0011;
            4'b0011: next_state = 4'b0111;
            4'b0100: next_state = 4'b0101;
            4'b0101: next_state = 4'b0111;
            4'b0110: next_state = 4'b0111;
            4'b0111: next_state = 4'b1111;
            4'b1000: next_state = 4'b1001;
            4'b1001: next_state = 4'b1011;
            4'b1010: next_state = 4'b1011;
            4'b1011: next_state = 4'b1111;
            4'b1100: next_state = 4'b1101;
            4'b1101: next_state = 4'b1111;
            4'b1110: next_state = 4'b1111;
            default: next_state = state; // Default to current state
          endcase
        end
      end

      2'b01: begin  // Exit sensor triggered, Enter sensor not triggered
        // Check the exit place validity and remove the car
        case (in[1:0])  // ExitPlace
          2'b00: if (state[0]) next_state = state & 4'b1110;  // Exit from spot 0
          2'b01: if (state[1]) next_state = state & 4'b1101;  // Exit from spot 1
          2'b10: if (state[2]) next_state = state & 4'b1011;  // Exit from spot 2
          2'b11: if (state[3]) next_state = state & 4'b0111;  // Exit from spot 3
          default: next_state = state; // Invalid exit place, keep current state
        endcase
      end

      default: next_state = state; // No valid input, keep current state
    endcase

    // Update the state at each clock cycle
    if (state != next_state) begin
      door_open_pulse <= 1'b1; // Generate the pulse
    end else begin
      door_open_pulse <= 1'b0; // No state change, no pulse
    end
    
    state <= next_state; // Assign the next state to the current state
  end
endmodule

ParkingSystem/FSM_tb.v
`timescale 1 ns / 1 ps

module FSM_tb;

  reg clk;
  reg [3:0] in;
  wire [3:0] state;
  wire door_open_pulse;

  FSM UUT (
      .clk(clk),
      .in(in),
      .state(state),
      .door_open_pulse(door_open_pulse)
  );

  initial begin

    $dumpvars(0, FSM_tb);
    $dumpfile("FSM_tb.vcd");
    clk = 0;
    forever #50 clk = ~clk;
  end

  initial begin
    in = 4'b0000;
    #100;

    in = 4'b1000;
    #100;

    in = 4'b0100;
    #100;

    in = 4'b1000;
    #100;

    in = 4'b1000;
    #100;

    in = 4'b1000;
    #100;

    #1000;

    $finish;
  end

endmodule

ParkingSystem/Capacity.v
module Capacity (
    input  [3:0] in,
    output [2:0] out
);

  // Intermediate signals for NOT operations
  wire not_in0, not_in1, not_in2, not_in3;

  // NOT gates to generate inverted inputs
  not U1 (not_in0, in[0]);
  not U2 (not_in1, in[1]);
  not U3 (not_in2, in[2]);
  not U4 (not_in3, in[3]);

  // out[2] = in[3] & in[2] & in[1] & in[0]
  wire and_out2;
  and U5 (and_out2, in[3], in[2], in[1], in[0]);

  // out[1] = (~in[3] + ~in[2] + ~in[0] + ~in[3])(in[3] + in[2] + in[1])(in[3] + in[2] + in[0])(in[3] + in[1] + in[0])(in[2] + in[1] + in[0])
  wire or1, or2, or3, or4, or5;

  // OR gates for the first part of out[1]
  or U6 (or1, not_in3, not_in2, not_in0, not_in1);

  // OR gates for the second part of out[1]
  or U7 (or2, in[3], in[2], in[1]);
  or U8 (or3, in[3], in[2], in[0]);
  or U9 (or4, in[3], in[1], in[0]);
  or U10 (or5, in[2], in[1], in[0]);

  // AND gate for final out[1]
  wire and_out1;
  and U11 (and_out1, or1, or2, or3, or4, or5);

  // out[0] = in[3] ^ in[2] ^ in[1] ^ in[0]
  wire xor_out1, xor_out2;

  xor U12 (xor_out1, in[3], in[2]);
  xor U13 (out[0], xor_out1, in[1], in[0]);

  // Assigning outputs
  assign out[2] = and_out2;
  assign out[1] = and_out1;

endmodule

ParkingSystem/Capacity_tb.v
`timescale 1 ns / 1 ps

module Capacity_tb;

  reg  [3:0] in;
  wire [2:0] out;

  Capacity UUT (
      .in (in),
      .out(out)
  );

  initial begin
    $dumpfile("Capacity_tb.vcd");
    $dumpvars(0, Capacity_tb);

  end

  initial begin
    in = 4'b0001;
    #100;

    in = 4'b0000;
    #100;

    in = 4'b0100;
    #100;

    in = 4'b1010;
    #100;

    in = 4'b1111;
    #100;

    in = 4'b1110;
    #100;

  end

endmodule

ParkingSystem/Capacity_tb.vcd
$date
	Thu Dec 26 18:02:01 2024
$end
$version
	Icarus Verilog
$end
$timescale
	1ps
$end
$scope module Capacity_tb $end
$var wire 3 ! out [2:0] $end
$var reg 4 " in [3:0] $end
$scope module UUT $end
$var wire 1 # and_out1 $end
$var wire 1 $ and_out2 $end
$var wire 4 % in [3:0] $end
$var wire 1 & not_in0 $end
$var wire 1 ' not_in1 $end
$var wire 1 ( not_in2 $end
$var wire 1 ) not_in3 $end
$var wire 1 * or1 $end
$var wire 1 + or2 $end
$var wire 1 , or3 $end
$var wire 1 - or4 $end
$var wire 1 . or5 $end
$var wire 1 / xor_out1 $end
$var wire 3 0 out [2:0] $end
$upscope $end
$upscope $end
$scope module FSM_tb $end
$var wire 4 1 state [3:0] $end
$var wire 1 2 door_open_pulse $end
$var reg 1 3 clk $end
$var reg 4 4 in [3:0] $end
$scope module UUT $end
$var wire 1 3 clk $end
$var wire 4 5 in [3:0] $end
$var reg 1 2 door_open_pulse $end
$var reg 4 6 next_state [3:0] $end
$var reg 4 7 state [3:0] $end
$upscope $end
$upscope $end
$scope module Location_tb $end
$var wire 3 8 encoded [2:0] $end
$var reg 4 9 in [3:0] $end
$scope module UUT $end
$var wire 1 : and0 $end
$var wire 1 ; and1 $end
$var wire 1 < and2 $end
$var wire 4 = in [3:0] $end
$var wire 1 > not_in0 $end
$var wire 1 ? not_in1 $end
$var wire 1 @ not_in2 $end
$var wire 1 A not_in3 $end
$var wire 3 B encoded [2:0] $end
$upscope $end
$upscope $end
$enddefinitions $end
$comment Show the parameter values. $end
$dumpall
$end
#0
$dumpvars
b1 B
1A
1@
1?
0>
b1 =
0<
0;
1:
b1 9
b1 8
b0 7
bx 6
b0 5
b0 4
03
02
b0 1
b1 0
0/
1.
1-
1,
0+
1*
1)
1(
1'
0&
b1 %
0$
0#
b1 "
b1 !
$end
#50000
b0 6
13
#100000
b0 8
b0 B
1>
0:
1&
0,
0-
0.
b0 !
b0 0
03
b0 9
b0 =
b1000 4
b1000 5
b0 "
b0 %
#150000
b1 1
b1 7
12
b1 6
13
#200000
b1 !
b1 0
0@
0(
1+
1,
1.
1/
03
b100 9
b100 =
b100 4
b100 5
b100 "
b100 %
#250000
b0 1
b0 7
b0 6
13
#300000
1#
0A
1@
0?
0'
1(
0)
1-
b10 !
b10 0
03
b1010 9
b1010 =
b1000 4
b1000 5
b1010 "
b1010 %
#350000
b1 1
b1 7
b1 6
13
#400000
0#
0*
0@
0>
0;
b101 8
b101 B
0&
0(
1$
0/
b100 !
b100 0
03
b1111 9
b1111 =
b1111 "
b1111 %
#450000
b11 1
b11 7
b11 6
13
#500000
1#
1*
1>
b0 8
b0 B
1&
0$
b11 !
b11 0
03
b1110 9
b1110 =
b1110 "
b1110 %
#550000
b111 1
b111 7
b111 6
13
#600000
b11 8
b11 B
1<
1A
0>
03
b111 9
b111 =
#650000
b1111 1
b1111 7
b1111 6
13
#700000
03
#750000
02
13
