ParkingSystem/FSM.v
module FSM (
    input  wire       clk,             // Clock signal
    input  wire [3:0] in,              // 4-bit input: {EnterSensor, ExitSensor, ExitPlace[1:0]}
    output reg  [3:0] state,           // 4-bit state representing the parking spots
    output reg        door_open_pulse  // Pulse for door open LED
);

  // Initialization
  initial begin
    state           = 4'b0000;  // Initial state: all parking spots empty
    door_open_pulse = 1'b0;     // Door open LED initially off
  end

reg [3:0] next_state; // Internal signal to store the next state

  always @(posedge clk) begin
    next_state = state;   // Default next state is the current state

    case (in[3:2])  // Check the input format
      2'b10: begin  // Enter sensor triggered, Exit sensor not triggered
        if (state != 4'b1111) begin  // Parking not full
          // Find the first empty parking spot (rightmost 0 becomes 1)
          case (state)
            4'b0000: next_state = 4'b0001;
            4'b0001: next_state = 4'b0011;
            4'b0010: next_state = 4'b0011;
            4'b0011: next_state = 4'b0111;
            4'b0100: next_state = 4'b0101;
            4'b0101: next_state = 4'b0111;
            4'b0110: next_state = 4'b0111;
            4'b0111: next_state = 4'b1111;
            4'b1000: next_state = 4'b1001;
            4'b1001: next_state = 4'b1011;
            4'b1010: next_state = 4'b1011;
            4'b1011: next_state = 4'b1111;
            4'b1100: next_state = 4'b1101;
            4'b1101: next_state = 4'b1111;
            4'b1110: next_state = 4'b1111;
            default: next_state = state; // Default to current state
          endcase
        end
      end

      2'b01: begin  // Exit sensor triggered, Enter sensor not triggered
        // Check the exit place validity and remove the car
        case (in[1:0])  // ExitPlace
          2'b00: if (state[0]) next_state = state & 4'b1110;  // Exit from spot 0
          2'b01: if (state[1]) next_state = state & 4'b1101;  // Exit from spot 1
          2'b10: if (state[2]) next_state = state & 4'b1011;  // Exit from spot 2
          2'b11: if (state[3]) next_state = state & 4'b0111;  // Exit from spot 3
          default: next_state = state; // Invalid exit place, keep current state
        endcase
      end

      default: next_state = state; // No valid input, keep current state
    endcase

    // Update the state at each clock cycle
    if (state != next_state) begin
      door_open_pulse <= 1'b1; // Generate the pulse
    end else begin
      door_open_pulse <= 1'b0; // No state change, no pulse
    end
    
    state <= next_state; // Assign the next state to the current state
  end
endmodule

ParkingSystem/ReadWrite_tb.v
module ReadWrite_tb;

  reg clk;
  reg entry;
  reg exit;
  reg [1:0] _switch;
  wire [3:0] state;
  wire open;

  integer file;
  integer file_out;
  integer status;

  FSM UUT (
      .clk(clk),
      .in({entry, exit, _switch}),
      .state(state),
      .door_open_pulse(open)
  );

  initial begin
    $dumpfile("ReadWrite_tb.vcd");
    $dumpvars(0, ReadWrite_tb);
    entry = 0;
    exit = 0;
    _switch = 2'b00;
    clk = 0;

    file = $fopen("input.txt", "r");
    file_out = $fopen("output.txt", "w");
    $display("the file content : %d", file);
    if (file == 0) begin
      $display("Error: Failed to open file.");
      $finish;
    end

    while (!$feof(
        file
    )) begin
      status = $fscanf(file, "%1b %1b %1b %1b\n", entry, exit, _switch[1], _switch[0]);
      if (status == 4) begin
        #100;
        $fwrite(file_out, "%b %s\n", state, open ? "open_door " : "");


      end else begin
        $display("Error: File format incorrect or incomplete data.");
        $finish;
      end
    end

    $fclose(file);
    $fclose(file_out);

    #200 $finish;
  end

    always begin
        #50;
        clk = ~clk;
    end
endmodule

ParkingSystem/Location.v
// The module returns the first 0 it founds in input.
// if there is any park it returns index. 0 to 3

// And if there isn't any park spot, full state, it returns 5. 101

module Location (
    input  wire [3:0] in,
    output wire [2:0] encoded
);

  wire not_in3, not_in2, not_in1, not_in0;
  wire and0, and1, and2;


  not U0 (not_in3, in[3]);
  not U1 (not_in2, in[2]);
  not U2 (not_in1, in[1]);
  not U3 (not_in0, in[0]);

  and U4 (and0, not_in1, in[0]);
  and U5 (and1, not_in2, in[1], in[0]);
  and U6 (and2, not_in3, in[2], in[1], in[0]);

  and U7 (encoded[2], in[3], in[2], in[1], in[0]);


  or U8 (encoded[1], and2, and1);
  or U9 (encoded[0], encoded[2], and2, and0);


endmodule

ParkingSystem/Location_tb.v
`timescale 1 ns / 1 ps

module Location_tb;

  reg  [3:0] in;
  wire [2:0] encoded;

  Location UUT (
      .in (in),
      .encoded(encoded)
  );

  initial begin
    $dumpfile("Location_tb.vcd");
    $dumpvars(0, Location_tb);

  end

  initial begin
    in = 4'b0001;
    #100;

    in = 4'b0000;
    #100;

    in = 4'b0100;
    #100;

    in = 4'b1010;
    #100;

    in = 4'b1111;
    #100;

    in = 4'b1110;
    #100;

    in = 4'b0111;
    #100;

  end

endmodule

ParkingSystem/Full_Light.v
module Full_Light (
    input  wire [3:0] fsm_state,     // 4-bit FSM state
    input  wire       enter_sensor,  // Enter sensor signal
    input  wire       exit_sensor,   // Exit sensor signal
    input  wire       clk,           // Clock signal for edge detection
    output reg        pulse          // Output pulse
);

  // Initialize outputs and internal signals
  initial begin
    pulse = 0;
  end

  // Internal register to detect the posedge of enter_sensor
  reg enter_sensor_prev;

  always @(posedge clk) begin
    // Edge detection and pulse generation
    if ((fsm_state == 4'b1111) &&  // FSM state is 15 (full parking lot)
        (exit_sensor == 0) &&  // Exit sensor is not active
        (enter_sensor == 1) &&  // Enter sensor is active
        (enter_sensor_prev == 0)) begin  // Detect rising edge of enter_sensor
      pulse <= 1;  // Generate a pulse
    end else begin
      pulse <= 0;  // Reset the pulse
    end

    // Update the previous state of enter_sensor
    enter_sensor_prev <= enter_sensor;
  end

endmodule

ParkingSystem/Full_Light_tb.v
`timescale 1 ns / 1 ps

module Full_Light_tb;

  reg [3:0] in;
  reg ent;
  reg ext;
  reg clk;
  wire pulse;

  Full_Light UUT (
      .fsm_state(in),
      .enter_sensor(ent),
      .exit_sensor(ext),
      .clk(clk),
      .pulse(pulse)
  );

  initial begin
    $dumpfile("Full_Light_tb.vcd");
    $dumpvars(0, Full_Light_tb);
    clk = 0;
    forever #50 clk = ~clk;
  end

  initial begin
    in  = 4'b0001;
    ent = 0;
    ext = 0;
    #100;

    in  = 4'b0000;
    ent = 1;
    ext = 0;
    #100;

    in  = 4'b1111;
    ent = 1;
    ext = 0;
    #100;

    in  = 4'b1010;
    ent = 1;
    ext = 0;
    #100;

    in  = 4'b1111;
    ent = 1;
    ext = 0;
    #100;

    in  = 4'b1111;
    ent = 0;
    ext = 0;
    #100;

    in  = 4'b1111;
    ent = 1;
    ext = 0;
    #100;

    in  = 4'b1100;
    ent = 1;
    ext = 0;
    #100;

    in  = 4'b1101;
    ent = 0;
    ext = 0;
    #100;

    in  = 4'b1111;
    ent = 1;
    ext = 0;
    #100;

  end

endmodule

ParkingSystem/FSM_tb.v
`timescale 1 ns / 1 ps

module FSM_tb;

  reg clk;
  reg [3:0] in;
  wire [3:0] state;
  wire door_open_pulse;

  FSM UUT (
      .clk(clk),
      .in(in),
      .state(state),
      .door_open_pulse(door_open_pulse)
  );

  initial begin

    $dumpvars(0, FSM_tb);
    $dumpfile("FSM_tb.vcd");
    clk = 0;
    forever #50 clk = ~clk;
  end

  initial begin
    in = 4'b0000;
    #100;

    in = 4'b1000;
    #100;

    in = 4'b0100;
    #100;

    in = 4'b1000;
    #100;

    in = 4'b1000;
    #100;

    in = 4'b1000;
    #100;

    #3000;

    $finish;
  end

endmodule

ParkingSystem/Capacity.v
module Capacity (
    input  [3:0] in,
    output [2:0] out
);

  // Intermediate signals for NOT operations
  wire not_in0, not_in1, not_in2, not_in3;

  // NOT gates to generate inverted inputs
  not U1 (not_in0, in[0]);
  not U2 (not_in1, in[1]);
  not U3 (not_in2, in[2]);
  not U4 (not_in3, in[3]);

  // out[2] = in[3] & in[2] & in[1] & in[0]
  wire and_out2;
  and U5 (and_out2, in[3], in[2], in[1], in[0]);

  // out[1] = (~in[3] + ~in[2] + ~in[0] + ~in[3])(in[3] + in[2] + in[1])(in[3] + in[2] + in[0])(in[3] + in[1] + in[0])(in[2] + in[1] + in[0])
  wire or1, or2, or3, or4, or5;

  // OR gates for the first part of out[1]
  or U6 (or1, not_in3, not_in2, not_in0, not_in1);

  // OR gates for the second part of out[1]
  or U7 (or2, in[3], in[2], in[1]);
  or U8 (or3, in[3], in[2], in[0]);
  or U9 (or4, in[3], in[1], in[0]);
  or U10 (or5, in[2], in[1], in[0]);

  // AND gate for final out[1]
  wire and_out1;
  and U11 (and_out1, or1, or2, or3, or4, or5);

  // out[0] = in[3] ^ in[2] ^ in[1] ^ in[0]
  wire xor_out1, xor_out2;

  xor U12 (xor_out1, in[3], in[2]);
  xor U13 (out[0], xor_out1, in[1], in[0]);

  // Assigning outputs
  assign out[2] = and_out2;
  assign out[1] = and_out1;

endmodule

ParkingSystem/Capacity_tb.v
`timescale 1 ns / 1 ps

module Capacity_tb;

  reg  [3:0] in;
  wire [2:0] out;

  Capacity UUT (
      .in (in),
      .out(out)
  );

  initial begin
    $dumpfile("Capacity_tb.vcd");
    $dumpvars(0, Capacity_tb);

  end

  initial begin
    in = 4'b0001;
    #100;

    in = 4'b0000;
    #100;

    in = 4'b0100;
    #100;

    in = 4'b1010;
    #100;

    in = 4'b1111;
    #100;

    in = 4'b1110;
    #100;

  end

endmodule

ParkingSystem/Capacity_tb.vcd
$date
	Fri Dec 27 19:46:26 2024
$end
$version
	Icarus Verilog
$end
$timescale
	1ps
$end
$scope module Capacity_tb $end
$var wire 3 ! out [2:0] $end
$var reg 4 " in [3:0] $end
$scope module UUT $end
$var wire 1 # and_out1 $end
$var wire 1 $ and_out2 $end
$var wire 4 % in [3:0] $end
$var wire 1 & not_in0 $end
$var wire 1 ' not_in1 $end
$var wire 1 ( not_in2 $end
$var wire 1 ) not_in3 $end
$var wire 1 * or1 $end
$var wire 1 + or2 $end
$var wire 1 , or3 $end
$var wire 1 - or4 $end
$var wire 1 . or5 $end
$var wire 1 / xor_out1 $end
$var wire 3 0 out [2:0] $end
$upscope $end
$upscope $end
$scope module FSM_tb $end
$var wire 4 1 state [3:0] $end
$var wire 1 2 door_open_pulse $end
$var reg 1 3 clk $end
$var reg 4 4 in [3:0] $end
$scope module UUT $end
$var wire 1 3 clk $end
$var wire 4 5 in [3:0] $end
$var reg 1 2 door_open_pulse $end
$var reg 4 6 next_state [3:0] $end
$var reg 4 7 state [3:0] $end
$upscope $end
$upscope $end
$scope module Full_Light_tb $end
$var wire 1 8 pulse $end
$var reg 1 9 clk $end
$var reg 1 : ent $end
$var reg 1 ; ext $end
$var reg 4 < in [3:0] $end
$scope module UUT $end
$var wire 1 9 clk $end
$var wire 1 : enter_sensor $end
$var wire 1 ; exit_sensor $end
$var wire 4 = fsm_state [3:0] $end
$var reg 1 > enter_sensor_prev $end
$var reg 1 8 pulse $end
$upscope $end
$upscope $end
$scope module Location_tb $end
$var wire 3 ? encoded [2:0] $end
$var reg 4 @ in [3:0] $end
$scope module UUT $end
$var wire 1 A and0 $end
$var wire 1 B and1 $end
$var wire 1 C and2 $end
$var wire 4 D in [3:0] $end
$var wire 1 E not_in0 $end
$var wire 1 F not_in1 $end
$var wire 1 G not_in2 $end
$var wire 1 H not_in3 $end
$var wire 3 I encoded [2:0] $end
$upscope $end
$upscope $end
$scope module ReadWrite_tb $end
$var wire 4 J state [3:0] $end
$var wire 1 K open $end
$var reg 2 L _switch [1:0] $end
$var reg 1 M clk $end
$var reg 1 N entry $end
$var reg 1 O exit $end
$var integer 32 P file [31:0] $end
$var integer 32 Q file_out [31:0] $end
$var integer 32 R status [31:0] $end
$scope module UUT $end
$var wire 1 M clk $end
$var wire 4 S in [3:0] $end
$var reg 1 K door_open_pulse $end
$var reg 4 T next_state [3:0] $end
$var reg 4 U state [3:0] $end
$upscope $end
$upscope $end
$enddefinitions $end
$comment Show the parameter values. $end
$dumpall
$end
#0
$dumpvars
b0 U
bx T
b0 S
b100 R
b10000000000000000000000000000100 Q
b10000000000000000000000000000011 P
0O
0N
0M
b0 L
0K
b0 J
b1 I
1H
1G
1F
0E
b1 D
0C
0B
1A
b1 @
b1 ?
x>
b1 =
b1 <
0;
0:
09
08
b0 7
bx 6
b0 5
b0 4
03
02
b0 1
b1 0
0/
1.
1-
1,
0+
1*
1)
1(
1'
0&
b1 %
0$
0#
b1 "
b1 !
$end
#50000
0>
b0 T
b0 6
1M
19
13
#100000
b0 ?
b0 I
1E
0A
1&
0,
0-
0.
b0 !
b0 0
0M
09
03
b1000 S
1N
b0 @
b0 D
1:
b0 <
b0 =
b1000 4
b1000 5
b0 "
b0 %
#150000
b1 J
b1 U
1K
1>
b1 1
b1 7
12
b1 T
b1 6
1M
19
13
#200000
b1 !
b1 0
0G
0(
1+
1,
1.
1/
0M
09
03
b1001 S
b1 L
b100 @
b100 D
b1111 <
b1111 =
b100 4
b100 5
b100 "
b100 %
#250000
b11 J
b11 U
b0 1
b0 7
b11 T
b0 6
1M
19
13
#300000
1#
0H
1G
0F
0'
1(
0)
1-
b10 !
b10 0
0M
09
03
b1 S
0N
b1010 @
b1010 D
b1010 <
b1010 =
b1000 4
b1000 5
b1010 "
b1010 %
#350000
0K
b1 1
b1 7
b1 6
1M
19
13
#400000
0#
0*
0G
0E
0B
b101 ?
b101 I
0&
0(
1$
0/
b100 !
b100 0
0M
09
03
b11 L
b1011 S
1N
b1111 @
b1111 D
b1111 <
b1111 =
b1111 "
b1111 %
#450000
b111 J
b111 U
1K
b11 1
b11 7
b111 T
b11 6
1M
19
13
#500000
1#
1*
1E
b0 ?
b0 I
1&
0$
b11 !
b11 0
0M
09
03
b1 L
1O
b101 S
0N
b1110 @
b1110 D
0:
b1110 "
b1110 %
#550000
b101 J
b101 U
0>
b111 1
b111 7
b101 T
b111 6
1M
19
13
#600000
b11 ?
b11 I
1C
1H
0E
0M
09
03
b0 L
0O
b1000 S
1N
b111 @
b111 D
1:
#650000
b111 J
b111 U
1>
18
b1111 1
b1111 7
b111 T
b1111 6
1M
19
13
#700000
0M
09
03
1O
b100 S
0N
b1100 <
b1100 =
#750000
b110 J
b110 U
08
02
b110 T
1M
19
13
#800000
0M
09
03
0:
b1101 <
b1101 =
#850000
0K
0>
1M
19
13
#900000
0M
09
03
b1 L
0O
b1001 S
1N
1:
b1111 <
b1111 =
#950000
b111 J
b111 U
1K
1>
18
b111 T
1M
19
13
#1000000
0M
09
03
b1000 S
b0 L
#1050000
b1111 J
b1111 U
08
b1111 T
1M
19
13
#1100000
0M
09
03
b1011 S
b11 L
#1150000
0K
1M
19
13
#1200000
0M
09
03
b1000 S
b0 L
#1250000
1M
19
13
#1300000
0M
09
03
b0 S
0N
#1350000
1M
19
13
#1400000
0M
09
03
b100 S
1O
#1450000
b1110 J
b1110 U
1K
b1110 T
1M
19
13
#1500000
0M
09
03
b11 L
b11 S
0O
#1550000
0K
1M
19
13
#1600000
0M
09
03
b10 L
b110 S
1O
#1650000
b1010 J
b1010 U
1K
b1010 T
1M
19
13
#1700000
0M
09
03
b111 S
b11 L
#1750000
b10 J
b10 U
b10 T
1M
19
13
#1800000
0M
09
03
b101 S
b1 L
#1850000
b0 J
b0 U
b0 T
1M
19
13
#1900000
0M
09
03
b0 L
b0 S
0O
#1950000
0K
1M
19
13
